{
  "trades": [
    {
      "ticker": "032403",
      "buy_date": "2011-01-27",
      "buy_price": 0.77,
      "sell_date": "2011-01-28",
      "sell_price": 0.77,
      "shares": 64935,
      "pl": 0.0,
      "pl_pct": 0.0,
      "sell_reason": "月RSI4=50<77"
    },
    {
      "ticker": "033645",
      "buy_date": "2011-01-27",
      "buy_price": 0.51,
      "sell_date": "2011-01-28",
      "sell_price": 0.44,
      "shares": 98039,
      "pl": -6862.73,
      "pl_pct": -13.73,
      "sell_reason": "止損-13.7%"
    },
    {
      "ticker": "034158",
      "buy_date": "2011-01-27",
      "buy_price": 0.48,
      "sell_date": "2011-01-28",
      "sell_price": 0.43,
      "shares": 104166,
      "pl": -5208.3,
      "pl_pct": -10.42,
      "sell_reason": "止損-10.4%"
    },
    {
      "ticker": "033889",
      "buy_date": "2011-01-27",
      "buy_price": 0.42,
      "sell_date": "2011-01-28",
      "sell_price": 0.38,
      "shares": 119047,
      "pl": -4761.88,
      "pl_pct": -9.52,
      "sell_reason": "月RSI4=50<77"
    },
    {
      "ticker": "033706",
      "buy_date": "2011-01-27",
      "buy_price": 0.74,
      "sell_date": "2011-01-28",
      "sell_price": 0.69,
      "shares": 67567,
      "pl": -3378.35,
      "pl_pct": -6.76,
      "sell_reason": "月RSI4=50<77"
    },
    {
      "ticker": "033710",
      "buy_date": "2011-01-28",
      "buy_price": 1.97,
      "sell_date": "2011-02-08",
      "sell_price": 1.94,
      "shares": 25380,
      "pl": -761.4,
      "pl_pct": -1.52,
      "sell_reason": "月RSI4=50<77"
    },
    {
      "ticker": "035714",
      "buy_date": "2011-01-28",
      "buy_price": 1.38,
      "sell_date": "2011-02-08",
      "sell_price": 1.15,
      "shares": 36231,
      "pl": -8333.13,
      "pl_pct": -16.67,
      "sell_reason": "止損-16.7%"
    },
    {
      "ticker": "035214",
      "buy_date": "2011-01-28",
      "buy_price": 2.91,
      "sell_date": "2011-02-08",
      "sell_price": 3.03,
      "shares": 17182,
      "pl": 2061.84,
      "pl_pct": 4.12,
      "sell_reason": "月RSI4=50<77"
    },
    {
      "ticker": "035044",
      "buy_date": "2011-01-28",
      "buy_price": 3.72,
      "sell_date": "2011-02-08",
      "sell_price": 3.54,
      "shares": 13440,
      "pl": -2419.2,
      "pl_pct": -4.84,
      "sell_reason": "月RSI4=50<77"
    },
    {
      "ticker": "035527",
      "buy_date": "2011-01-28",
      "buy_price": 1.42,
      "sell_date": "2011-02-08",
      "sell_price": 1.25,
      "shares": 35211,
      "pl": -5985.87,
      "pl_pct": -11.97,
      "sell_reason": "止損-12.0%"
    },
    {
      "ticker": "03730P",
      "buy_date": "2011-02-08",
      "buy_price": 0.54,
      "sell_date": "2011-02-09",
      "sell_price": 0.56,
      "shares": 92592,
      "pl": 1851.84,
      "pl_pct": 3.7,
      "sell_reason": "月RSI4=50<77"
    },
    {
      "ticker": "035990",
      "buy_date": "2011-02-08",
      "buy_price": 1.87,
      "sell_date": "2011-02-09",
      "sell_price": 2.01,
      "shares": 26737,
      "pl": 3743.18,
      "pl_pct": 7.49,
      "sell_reason": "月RSI4=50<77"
    },
    {
      "ticker": "034979",
      "buy_date": "2011-02-08",
      "buy_price": 2.82,
      "sell_date": "2011-02-09",
      "sell_price": 2.78,
      "shares": 17730,
      "pl": -709.2,
      "pl_pct": -1.42,
      "sell_reason": "月RSI4=50<77"
    },
    {
      "ticker": "2536",
      "buy_date": "2011-02-08",
      "buy_price": 40.05,
      "sell_date": "2011-02-09",
      "sell_price": 40.05,
      "shares": 1248,
      "pl": 0.0,
      "pl_pct": 0.0,
      "sell_reason": "月RSI4=50<77"
    },
    {
      "ticker": "036025",
      "buy_date": "2011-02-09",
      "buy_price": 2.29,
      "sell_date": "2011-02-10",
      "sell_price": 2.12,
      "shares": 21834,
      "pl": -3711.78,
      "pl_pct": -7.42,
      "sell_reason": "止損-7.4%"
    },
    {
      "ticker": "036080",
      "buy_date": "2011-02-09",
      "buy_price": 2.17,
      "sell_date": "2011-02-10",
      "sell_price": 2.04,
      "shares": 23041,
      "pl": -2995.33,
      "pl_pct": -5.99,
      "sell_reason": "月RSI4=50<77"
    },
    {
      "ticker": "035990",
      "buy_date": "2011-02-09",
      "buy_price": 2.01,
      "sell_date": "2011-02-10",
      "sell_price": 1.83,
      "shares": 24875,
      "pl": -4477.5,
      "pl_pct": -8.96,
      "sell_reason": "止損-9.0%"
    },
    {
      "ticker": "033460",
      "buy_date": "2011-02-09",
      "buy_price": 0.59,
      "sell_date": "2011-02-10",
      "sell_price": 0.56,
      "shares": 84745,
      "pl": -2542.35,
      "pl_pct": -5.08,
      "sell_reason": "月RSI4=50<77"
    },
    {
      "ticker": "034928",
      "buy_date": "2011-02-09",
      "buy_price": 1.7,
      "sell_date": "2011-02-10",
      "sell_price": 1.52,
      "shares": 29411,
      "pl": -5293.98,
      "pl_pct": -10.59,
      "sell_reason": "止損-10.6%"
    },
    {
      "ticker": "033680",
      "buy_date": "2011-02-08",
      "buy_price": 1.32,
      "sell_date": "2011-02-11",
      "sell_price": 0.8,
      "shares": 37878,
      "pl": -19696.56,
      "pl_pct": -39.39,
      "sell_reason": "止損-39.4%"
    },
    {
      "ticker": "036511",
      "buy_date": "2011-03-31",
      "buy_price": 0.21,
      "sell_date": "2011-04-01",
      "sell_price": 0.34,
      "shares": 238095,
      "pl": 30952.35,
      "pl_pct": 61.9,
      "sell_reason": "月RSI4=50<77"
    },
    {
      "ticker": "5388",
      "buy_date": "2011-03-31",
      "buy_price": 31.4,
      "sell_date": "2011-04-01",
      "sell_price": 31.6,
      "shares": 1592,
      "pl": 318.4,
      "pl_pct": 0.64,
      "sell_reason": "月RSI4=50<77"
    },
    {
      "ticker": "035654",
      "buy_date": "2011-03-31",
      "buy_price": 0.75,
      "sell_date": "2011-04-01",
      "sell_price": 0.75,
      "shares": 66666,
      "pl": 0.0,
      "pl_pct": 0.0,
      "sell_reason": "月RSI4=50<77"
    },
    {
      "ticker": "2332",
      "buy_date": "2011-03-31",
      "buy_price": 27.4,
      "sell_date": "2011-04-01",
      "sell_price": 27.8,
      "shares": 1824,
      "pl": 729.6,
      "pl_pct": 1.46,
      "sell_reason": "月RSI4=50<77"
    },
    {
      "ticker": "3015",
      "buy_date": "2011-03-31",
      "buy_price": 33.42,
      "sell_date": "2011-04-01",
      "sell_price": 33.52,
      "shares": 1495,
      "pl": 134.69,
      "pl_pct": 0.27,
      "sell_reason": "月RSI4=50<77"
    },
    {
      "ticker": "036511",
      "buy_date": "2011-04-01",
      "buy_price": 0.34,
      "sell_date": "2011-04-06",
      "sell_price": 0.42,
      "shares": 147058,
      "pl": 11764.64,
      "pl_pct": 23.53,
      "sell_reason": "月RSI4=50<77"
    },
    {
      "ticker": "1439",
      "buy_date": "2011-04-01",
      "buy_price": 28.12,
      "sell_date": "2011-04-06",
      "sell_price": 28.23,
      "shares": 1777,
      "pl": 196.22,
      "pl_pct": 0.39,
      "sell_reason": "月RSI4=50<77"
    },
    {
      "ticker": "2107",
      "buy_date": "2011-04-01",
      "buy_price": 28.15,
      "sell_date": "2011-04-06",
      "sell_price": 28.4,
      "shares": 1776,
      "pl": 444.0,
      "pl_pct": 0.89,
      "sell_reason": "月RSI4=50<77"
    },
    {
      "ticker": "5388",
      "buy_date": "2011-04-01",
      "buy_price": 31.6,
      "sell_date": "2011-04-06",
      "sell_price": 31.5,
      "shares": 1582,
      "pl": -158.2,
      "pl_pct": -0.32,
      "sell_reason": "月RSI4=50<77"
    },
    {
      "ticker": "1308",
      "buy_date": "2011-04-01",
      "buy_price": 51.1,
      "sell_date": "2011-04-06",
      "sell_price": 52.7,
      "shares": 978,
      "pl": 1564.8,
      "pl_pct": 3.13,
      "sell_reason": "月RSI4=50<77"
    },
    {
      "ticker": "036225",
      "buy_date": "2011-04-06",
      "buy_price": 0.67,
      "sell_date": "2011-04-07",
      "sell_price": 0.66,
      "shares": 74626,
      "pl": -746.26,
      "pl_pct": -1.49,
      "sell_reason": "月RSI4=50<77"
    },
    {
      "ticker": "2459",
      "buy_date": "2011-04-06",
      "buy_price": 32.75,
      "sell_date": "2011-04-07",
      "sell_price": 32.75,
      "shares": 1526,
      "pl": 0.0,
      "pl_pct": 0.0,
      "sell_reason": "月RSI4=50<77"
    },
    {
      "ticker": "036511",
      "buy_date": "2011-04-06",
      "buy_price": 0.42,
      "sell_date": "2011-04-07",
      "sell_price": 0.54,
      "shares": 119047,
      "pl": 14285.64,
      "pl_pct": 28.57,
      "sell_reason": "月RSI4=50<77"
    },
    {
      "ticker": "036082",
      "buy_date": "2011-04-06",
      "buy_price": 0.51,
      "sell_date": "2011-04-07",
      "sell_price": 0.48,
      "shares": 98039,
      "pl": -2941.17,
      "pl_pct": -5.88,
      "sell_reason": "月RSI4=50<77"
    },
    {
      "ticker": "1201",
      "buy_date": "2011-04-07",
      "buy_price": 33.4,
      "sell_date": "2011-04-08",
      "sell_price": 33.15,
      "shares": 1497,
      "pl": -374.25,
      "pl_pct": -0.75,
      "sell_reason": "月RSI4=50<77"
    },
    {
      "ticker": "3015",
      "buy_date": "2011-04-07",
      "buy_price": 34.1,
      "sell_date": "2011-04-08",
      "sell_price": 34.1,
      "shares": 1466,
      "pl": 0.0,
      "pl_pct": 0.0,
      "sell_reason": "月RSI4=50<77"
    },
    {
      "ticker": "2460",
      "buy_date": "2011-04-07",
      "buy_price": 19.7,
      "sell_date": "2011-04-08",
      "sell_price": 20.0,
      "shares": 2538,
      "pl": 761.4,
      "pl_pct": 1.52,
      "sell_reason": "月RSI4=50<77"
    },
    {
      "ticker": "036864",
      "buy_date": "2011-04-07",
      "buy_price": 1.03,
      "sell_date": "2011-04-08",
      "sell_price": 1.23,
      "shares": 48543,
      "pl": 9708.6,
      "pl_pct": 19.42,
      "sell_reason": "月RSI4=50<77"
    },
    {
      "ticker": "036013",
      "buy_date": "2011-04-07",
      "buy_price": 0.28,
      "sell_date": "2011-04-08",
      "sell_price": 0.33,
      "shares": 178571,
      "pl": 8928.55,
      "pl_pct": 17.86,
      "sell_reason": "月RSI4=50<77"
    },
    {
      "ticker": "036055",
      "buy_date": "2011-04-08",
      "buy_price": 1.06,
      "sell_date": "2011-04-11",
      "sell_price": 1.07,
      "shares": 47169,
      "pl": 471.7,
      "pl_pct": 0.94,
      "sell_reason": "月RSI4=50<77"
    },
    {
      "ticker": "036544",
      "buy_date": "2011-04-08",
      "buy_price": 0.39,
      "sell_date": "2011-04-11",
      "sell_price": 0.42,
      "shares": 128205,
      "pl": 3846.15,
      "pl_pct": 7.69,
      "sell_reason": "月RSI4=50<77"
    },
    {
      "ticker": "036864",
      "buy_date": "2011-04-08",
      "buy_price": 1.23,
      "sell_date": "2011-04-11",
      "sell_price": 1.22,
      "shares": 40650,
      "pl": -406.5,
      "pl_pct": -0.81,
      "sell_reason": "月RSI4=50<77"
    },
    {
      "ticker": "036013",
      "buy_date": "2011-04-08",
      "buy_price": 0.33,
      "sell_date": "2011-04-11",
      "sell_price": 0.37,
      "shares": 151515,
      "pl": 6060.6,
      "pl_pct": 12.12,
      "sell_reason": "月RSI4=50<77"
    },
    {
      "ticker": "033950",
      "buy_date": "2011-04-08",
      "buy_price": 0.41,
      "sell_date": "2011-04-11",
      "sell_price": 0.35,
      "shares": 121951,
      "pl": -7317.06,
      "pl_pct": -14.63,
      "sell_reason": "止損-14.6%"
    },
    {
      "ticker": "1615",
      "buy_date": "2011-04-11",
      "buy_price": 15.8,
      "sell_date": "2011-04-12",
      "sell_price": 16.65,
      "shares": 3164,
      "pl": 2689.4,
      "pl_pct": 5.38,
      "sell_reason": "月RSI4=50<77"
    },
    {
      "ticker": "910861",
      "buy_date": "2011-04-11",
      "buy_price": 27.1,
      "sell_date": "2011-04-12",
      "sell_price": 27.3,
      "shares": 1845,
      "pl": 369.0,
      "pl_pct": 0.74,
      "sell_reason": "月RSI4=50<77"
    },
    {
      "ticker": "2854",
      "buy_date": "2011-04-11",
      "buy_price": 20.85,
      "sell_date": "2011-04-12",
      "sell_price": 21.0,
      "shares": 2398,
      "pl": 359.7,
      "pl_pct": 0.72,
      "sell_reason": "月RSI4=50<77"
    },
    {
      "ticker": "1323",
      "buy_date": "2011-04-11",
      "buy_price": 24.14,
      "sell_date": "2011-04-12",
      "sell_price": 23.8,
      "shares": 2071,
      "pl": -714.23,
      "pl_pct": -1.43,
      "sell_reason": "月RSI4=50<77"
    },
    {
      "ticker": "1201",
      "buy_date": "2011-04-13",
      "buy_price": 33.25,
      "sell_date": "2011-04-14",
      "sell_price": 33.2,
      "shares": 1503,
      "pl": -75.15,
      "pl_pct": -0.15,
      "sell_reason": "月RSI4=50<77"
    },
    {
      "ticker": "3022",
      "buy_date": "2011-04-13",
      "buy_price": 60.3,
      "sell_date": "2011-04-14",
      "sell_price": 60.7,
      "shares": 829,
      "pl": 331.6,
      "pl_pct": 0.66,
      "sell_reason": "月RSI4=50<77"
    },
    {
      "ticker": "9942",
      "buy_date": "2011-04-13",
      "buy_price": 51.3,
      "sell_date": "2011-04-14",
      "sell_price": 51.9,
      "shares": 974,
      "pl": 584.4,
      "pl_pct": 1.17,
      "sell_reason": "月RSI4=50<77"
    },
    {
      "ticker": "6235",
      "buy_date": "2011-04-13",
      "buy_price": 6.65,
      "sell_date": "2011-04-14",
      "sell_price": 6.58,
      "shares": 7518,
      "pl": -526.26,
      "pl_pct": -1.05,
      "sell_reason": "月RSI4=50<77"
    },
    {
      "ticker": "2395",
      "buy_date": "2011-04-13",
      "buy_price": 91.5,
      "sell_date": "2011-04-14",
      "sell_price": 92.4,
      "shares": 546,
      "pl": 491.4,
      "pl_pct": 0.98,
      "sell_reason": "月RSI4=50<77"
    },
    {
      "ticker": "03740P",
      "buy_date": "2011-04-06",
      "buy_price": 0.99,
      "sell_date": "2011-04-15",
      "sell_price": 1.02,
      "shares": 50505,
      "pl": 1515.15,
      "pl_pct": 3.03,
      "sell_reason": "月RSI4=50<77"
    },
    {
      "ticker": "036331",
      "buy_date": "2011-04-11",
      "buy_price": 2.86,
      "sell_date": "2011-04-15",
      "sell_price": 2.1,
      "shares": 17482,
      "pl": -13286.32,
      "pl_pct": -26.57,
      "sell_reason": "止損-26.6%"
    },
    {
      "ticker": "035321",
      "buy_date": "2011-04-14",
      "buy_price": 0.58,
      "sell_date": "2011-04-15",
      "sell_price": 0.49,
      "shares": 86206,
      "pl": -7758.54,
      "pl_pct": -15.52,
      "sell_reason": "止損-15.5%"
    },
    {
      "ticker": "036519",
      "buy_date": "2011-04-14",
      "buy_price": 1.65,
      "sell_date": "2011-04-15",
      "sell_price": 1.54,
      "shares": 30303,
      "pl": -3333.33,
      "pl_pct": -6.67,
      "sell_reason": "月RSI4=50<77"
    },
    {
      "ticker": "035424",
      "buy_date": "2011-04-14",
      "buy_price": 2.6,
      "sell_date": "2011-04-15",
      "sell_price": 2.45,
      "shares": 19230,
      "pl": -2884.5,
      "pl_pct": -5.77,
      "sell_reason": "月RSI4=50<77"
    },
    {
      "ticker": "1615",
      "buy_date": "2011-04-14",
      "buy_price": 17.0,
      "sell_date": "2011-04-15",
      "sell_price": 17.05,
      "shares": 2941,
      "pl": 147.05,
      "pl_pct": 0.29,
      "sell_reason": "月RSI4=50<77"
    },
    {
      "ticker": "037272",
      "buy_date": "2011-04-14",
      "buy_price": 0.74,
      "sell_date": "2011-04-20",
      "sell_price": 0.67,
      "shares": 67567,
      "pl": -4729.69,
      "pl_pct": -9.46,
      "sell_reason": "月RSI4=50<77"
    },
    {
      "ticker": "2801",
      "buy_date": "2011-04-20",
      "buy_price": 22.5,
      "sell_date": "2011-04-21",
      "sell_price": 23.43,
      "shares": 2222,
      "pl": 2057.57,
      "pl_pct": 4.12,
      "sell_reason": "月RSI4=50<77"
    },
    {
      "ticker": "9904",
      "buy_date": "2011-04-20",
      "buy_price": 26.85,
      "sell_date": "2011-04-21",
      "sell_price": 27.09,
      "shares": 1862,
      "pl": 452.05,
      "pl_pct": 0.9,
      "sell_reason": "月RSI4=50<77"
    },
    {
      "ticker": "035926",
      "buy_date": "2011-04-20",
      "buy_price": 0.38,
      "sell_date": "2011-04-21",
      "sell_price": 0.6,
      "shares": 131578,
      "pl": 28947.16,
      "pl_pct": 57.89,
      "sell_reason": "月RSI4=50<77"
    },
    {
      "ticker": "034522",
      "buy_date": "2011-04-20",
      "buy_price": 1.33,
      "sell_date": "2011-04-21",
      "sell_price": 1.44,
      "shares": 37593,
      "pl": 4135.23,
      "pl_pct": 8.27,
      "sell_reason": "月RSI4=50<77"
    },
    {
      "ticker": "034905",
      "buy_date": "2011-04-20",
      "buy_price": 1.46,
      "sell_date": "2011-04-21",
      "sell_price": 1.95,
      "shares": 34246,
      "pl": 16780.54,
      "pl_pct": 33.56,
      "sell_reason": "月RSI4=50<77"
    },
    {
      "ticker": "036650",
      "buy_date": "2011-04-21",
      "buy_price": 0.86,
      "sell_date": "2011-04-22",
      "sell_price": 0.8,
      "shares": 58139,
      "pl": -3488.34,
      "pl_pct": -6.98,
      "sell_reason": "月RSI4=50<77"
    },
    {
      "ticker": "035122",
      "buy_date": "2011-04-21",
      "buy_price": 0.26,
      "sell_date": "2011-04-22",
      "sell_price": 0.24,
      "shares": 192307,
      "pl": -3846.14,
      "pl_pct": -7.69,
      "sell_reason": "月RSI4=50<77"
    },
    {
      "ticker": "036864",
      "buy_date": "2011-04-21",
      "buy_price": 1.37,
      "sell_date": "2011-04-22",
      "sell_price": 1.41,
      "shares": 36496,
      "pl": 1459.84,
      "pl_pct": 2.92,
      "sell_reason": "月RSI4=50<77"
    },
    {
      "ticker": "2880",
      "buy_date": "2011-04-21",
      "buy_price": 22.9,
      "sell_date": "2011-04-22",
      "sell_price": 23.0,
      "shares": 2183,
      "pl": 218.3,
      "pl_pct": 0.44,
      "sell_reason": "月RSI4=50<77"
    },
    {
      "ticker": "1717",
      "buy_date": "2011-04-21",
      "buy_price": 32.32,
      "sell_date": "2011-04-22",
      "sell_price": 32.65,
      "shares": 1546,
      "pl": 501.14,
      "pl_pct": 1.0,
      "sell_reason": "月RSI4=50<77"
    },
    {
      "ticker": "2401",
      "buy_date": "2011-04-22",
      "buy_price": 17.62,
      "sell_date": "2011-04-25",
      "sell_price": 17.34,
      "shares": 2837,
      "pl": -785.13,
      "pl_pct": -1.57,
      "sell_reason": "月RSI4=50<77"
    },
    {
      "ticker": "2880",
      "buy_date": "2011-04-22",
      "buy_price": 23.0,
      "sell_date": "2011-04-25",
      "sell_price": 23.25,
      "shares": 2173,
      "pl": 543.25,
      "pl_pct": 1.09,
      "sell_reason": "月RSI4=50<77"
    },
    {
      "ticker": "036734",
      "buy_date": "2011-04-22",
      "buy_price": 0.51,
      "sell_date": "2011-04-25",
      "sell_price": 0.4,
      "shares": 98039,
      "pl": -10784.29,
      "pl_pct": -21.57,
      "sell_reason": "止損-21.6%"
    },
    {
      "ticker": "034377",
      "buy_date": "2011-04-22",
      "buy_price": 0.52,
      "sell_date": "2011-04-25",
      "sell_price": 0.43,
      "shares": 96153,
      "pl": -8653.77,
      "pl_pct": -17.31,
      "sell_reason": "止損-17.3%"
    },
    {
      "ticker": "2882",
      "buy_date": "2011-04-25",
      "buy_price": 46.29,
      "sell_date": "2011-04-26",
      "sell_price": 45.09,
      "shares": 1080,
      "pl": -1300.57,
      "pl_pct": -2.6,
      "sell_reason": "月RSI4=50<77"
    },
    {
      "ticker": "035918",
      "buy_date": "2011-04-25",
      "buy_price": 0.97,
      "sell_date": "2011-04-26",
      "sell_price": 0.65,
      "shares": 51546,
      "pl": -16494.72,
      "pl_pct": -32.99,
      "sell_reason": "止損-33.0%"
    },
    {
      "ticker": "2101",
      "buy_date": "2011-04-25",
      "buy_price": 43.19,
      "sell_date": "2011-04-26",
      "sell_price": 42.86,
      "shares": 1157,
      "pl": -380.61,
      "pl_pct": -0.76,
      "sell_reason": "月RSI4=50<77"
    },
    {
      "ticker": "2108",
      "buy_date": "2011-04-25",
      "buy_price": 29.4,
      "sell_date": "2011-04-26",
      "sell_price": 29.2,
      "shares": 1700,
      "pl": -340.0,
      "pl_pct": -0.68,
      "sell_reason": "月RSI4=50<77"
    },
    {
      "ticker": "035309",
      "buy_date": "2011-04-25",
      "buy_price": 1.49,
      "sell_date": "2011-04-26",
      "sell_price": 1.05,
      "shares": 33557,
      "pl": -14765.08,
      "pl_pct": -29.53,
      "sell_reason": "止損-29.5%"
    },
    {
      "ticker": "034480",
      "buy_date": "2011-04-22",
      "buy_price": 2.72,
      "sell_date": "2011-04-27",
      "sell_price": 2.09,
      "shares": 18382,
      "pl": -11580.66,
      "pl_pct": -23.16,
      "sell_reason": "止損-23.2%"
    },
    {
      "ticker": "036672",
      "buy_date": "2011-04-26",
      "buy_price": 0.82,
      "sell_date": "2011-04-27",
      "sell_price": 0.95,
      "shares": 60975,
      "pl": 7926.75,
      "pl_pct": 15.85,
      "sell_reason": "月RSI4=50<77"
    },
    {
      "ticker": "2421",
      "buy_date": "2011-04-26",
      "buy_price": 25.7,
      "sell_date": "2011-04-27",
      "sell_price": 25.5,
      "shares": 1945,
      "pl": -389.0,
      "pl_pct": -0.78,
      "sell_reason": "月RSI4=50<77"
    },
    {
      "ticker": "1439",
      "buy_date": "2011-04-26",
      "buy_price": 30.55,
      "sell_date": "2011-04-27",
      "sell_price": 29.81,
      "shares": 1636,
      "pl": -1204.37,
      "pl_pct": -2.41,
      "sell_reason": "月RSI4=50<77"
    },
    {
      "ticker": "035982",
      "buy_date": "2011-04-26",
      "buy_price": 3.0,
      "sell_date": "2011-04-27",
      "sell_price": 3.94,
      "shares": 16666,
      "pl": 15666.04,
      "pl_pct": 31.33,
      "sell_reason": "月RSI4=50<77"
    },
    {
      "ticker": "037892",
      "buy_date": "2011-04-26",
      "buy_price": 1.51,
      "sell_date": "2011-04-27",
      "sell_price": 1.52,
      "shares": 33112,
      "pl": 331.12,
      "pl_pct": 0.66,
      "sell_reason": "月RSI4=50<77"
    },
    {
      "ticker": "036650",
      "buy_date": "2011-04-27",
      "buy_price": 0.87,
      "sell_date": "2011-04-28",
      "sell_price": 0.75,
      "shares": 57471,
      "pl": -6896.52,
      "pl_pct": -13.79,
      "sell_reason": "止損-13.8%"
    },
    {
      "ticker": "2108",
      "buy_date": "2011-04-27",
      "buy_price": 29.6,
      "sell_date": "2011-04-28",
      "sell_price": 29.25,
      "shares": 1689,
      "pl": -591.15,
      "pl_pct": -1.18,
      "sell_reason": "月RSI4=50<77"
    },
    {
      "ticker": "036819",
      "buy_date": "2011-04-27",
      "buy_price": 0.53,
      "sell_date": "2011-04-28",
      "sell_price": 0.56,
      "shares": 94339,
      "pl": 2830.17,
      "pl_pct": 5.66,
      "sell_reason": "月RSI4=50<77"
    },
    {
      "ticker": "035508",
      "buy_date": "2011-04-27",
      "buy_price": 0.24,
      "sell_date": "2011-04-28",
      "sell_price": 0.21,
      "shares": 208333,
      "pl": -6249.99,
      "pl_pct": -12.5,
      "sell_reason": "止損-12.5%"
    },
    {
      "ticker": "9933",
      "buy_date": "2011-04-28",
      "buy_price": 34.26,
      "sell_date": "2011-04-29",
      "sell_price": 34.74,
      "shares": 1459,
      "pl": 700.14,
      "pl_pct": 1.4,
      "sell_reason": "月RSI4=50<77"
    },
    {
      "ticker": "036924",
      "buy_date": "2011-04-28",
      "buy_price": 1.69,
      "sell_date": "2011-04-29",
      "sell_price": 1.79,
      "shares": 29585,
      "pl": 2958.5,
      "pl_pct": 5.92,
      "sell_reason": "月RSI4=50<77"
    },
    {
      "ticker": "036865",
      "buy_date": "2011-04-28",
      "buy_price": 3.99,
      "sell_date": "2011-04-29",
      "sell_price": 4.33,
      "shares": 12531,
      "pl": 4260.54,
      "pl_pct": 8.52,
      "sell_reason": "月RSI4=50<77"
    },
    {
      "ticker": "037393",
      "buy_date": "2011-04-28",
      "buy_price": 1.99,
      "sell_date": "2011-04-29",
      "sell_price": 2.17,
      "shares": 25125,
      "pl": 4522.5,
      "pl_pct": 9.05,
      "sell_reason": "月RSI4=50<77"
    },
    {
      "ticker": "037297",
      "buy_date": "2011-04-28",
      "buy_price": 4.25,
      "sell_date": "2011-04-29",
      "sell_price": 4.68,
      "shares": 11764,
      "pl": 5058.52,
      "pl_pct": 10.12,
      "sell_reason": "月RSI4=50<77"
    },
    {
      "ticker": "2882",
      "buy_date": "2011-04-29",
      "buy_price": 46.05,
      "sell_date": "2011-05-03",
      "sell_price": 45.76,
      "shares": 1085,
      "pl": -313.58,
      "pl_pct": -0.63,
      "sell_reason": "月RSI4=50<77"
    },
    {
      "ticker": "2530",
      "buy_date": "2011-04-29",
      "buy_price": 15.44,
      "sell_date": "2011-05-03",
      "sell_price": 15.39,
      "shares": 3239,
      "pl": -161.27,
      "pl_pct": -0.32,
      "sell_reason": "月RSI4=50<77"
    },
    {
      "ticker": "036519",
      "buy_date": "2011-04-29",
      "buy_price": 2.0,
      "sell_date": "2011-05-03",
      "sell_price": 1.86,
      "shares": 25000,
      "pl": -3500.0,
      "pl_pct": -7.0,
      "sell_reason": "月RSI4=50<77"
    },
    {
      "ticker": "037967",
      "buy_date": "2011-04-29",
      "buy_price": 1.29,
      "sell_date": "2011-05-03",
      "sell_price": 1.33,
      "shares": 38759,
      "pl": 1550.36,
      "pl_pct": 3.1,
      "sell_reason": "月RSI4=50<77"
    },
    {
      "ticker": "037297",
      "buy_date": "2011-04-29",
      "buy_price": 4.68,
      "sell_date": "2011-05-03",
      "sell_price": 4.82,
      "shares": 10683,
      "pl": 1495.62,
      "pl_pct": 2.99,
      "sell_reason": "月RSI4=50<77"
    },
    {
      "ticker": "04020P",
      "buy_date": "2011-05-03",
      "buy_price": 1.0,
      "sell_date": "2011-05-04",
      "sell_price": 0.89,
      "shares": 50000,
      "pl": -5500.0,
      "pl_pct": -11.0,
      "sell_reason": "止損-11.0%"
    },
    {
      "ticker": "039052",
      "buy_date": "2011-05-03",
      "buy_price": 3.0,
      "sell_date": "2011-05-04",
      "sell_price": 3.89,
      "shares": 16666,
      "pl": 14832.74,
      "pl_pct": 29.67,
      "sell_reason": "月RSI4=50<77"
    },
    {
      "ticker": "039069",
      "buy_date": "2011-05-03",
      "buy_price": 1.93,
      "sell_date": "2011-05-04",
      "sell_price": 2.59,
      "shares": 25906,
      "pl": 17097.96,
      "pl_pct": 34.2,
      "sell_reason": "月RSI4=50<77"
    },
    {
      "ticker": "037478",
      "buy_date": "2011-05-03",
      "buy_price": 0.97,
      "sell_date": "2011-05-04",
      "sell_price": 0.96,
      "shares": 51546,
      "pl": -515.46,
      "pl_pct": -1.03,
      "sell_reason": "月RSI4=50<77"
    },
    {
      "ticker": "04149P",
      "buy_date": "2011-05-03",
      "buy_price": 2.19,
      "sell_date": "2011-05-04",
      "sell_price": 2.18,
      "shares": 22831,
      "pl": -228.31,
      "pl_pct": -0.46,
      "sell_reason": "月RSI4=50<77"
    },
    {
      "ticker": "2833",
      "buy_date": "2011-05-04",
      "buy_price": 27.79,
      "sell_date": "2011-05-05",
      "sell_price": 28.32,
      "shares": 1799,
      "pl": 949.87,
      "pl_pct": 1.9,
      "sell_reason": "月RSI4=50<77"
    },
    {
      "ticker": "035325",
      "buy_date": "2011-05-04",
      "buy_price": 0.38,
      "sell_date": "2011-05-05",
      "sell_price": 0.35,
      "shares": 131578,
      "pl": -3947.34,
      "pl_pct": -7.89,
      "sell_reason": "月RSI4=50<77"
    },
    {
      "ticker": "036420",
      "buy_date": "2011-05-04",
      "buy_price": 1.0,
      "sell_date": "2011-05-05",
      "sell_price": 1.19,
      "shares": 50000,
      "pl": 9500.0,
      "pl_pct": 19.0,
      "sell_reason": "月RSI4=50<77"
    },
    {
      "ticker": "3030",
      "buy_date": "2011-05-04",
      "buy_price": 55.87,
      "sell_date": "2011-05-05",
      "sell_price": 54.66,
      "shares": 894,
      "pl": -1082.27,
      "pl_pct": -2.17,
      "sell_reason": "月RSI4=50<77"
    },
    {
      "ticker": "9151",
      "buy_date": "2011-05-04",
      "buy_price": 26.45,
      "sell_date": "2011-05-05",
      "sell_price": 26.15,
      "shares": 1890,
      "pl": -567.0,
      "pl_pct": -1.13,
      "sell_reason": "月RSI4=50<77"
    },
    {
      "ticker": "036389",
      "buy_date": "2011-05-05",
      "buy_price": 1.89,
      "sell_date": "2011-05-06",
      "sell_price": 1.72,
      "shares": 26455,
      "pl": -4497.35,
      "pl_pct": -8.99,
      "sell_reason": "月RSI4=50<77"
    },
    {
      "ticker": "2379",
      "buy_date": "2011-05-05",
      "buy_price": 59.9,
      "sell_date": "2011-05-06",
      "sell_price": 59.4,
      "shares": 834,
      "pl": -417.0,
      "pl_pct": -0.83,
      "sell_reason": "月RSI4=50<77"
    },
    {
      "ticker": "6153",
      "buy_date": "2011-05-05",
      "buy_price": 60.39,
      "sell_date": "2011-05-06",
      "sell_price": 59.79,
      "shares": 827,
      "pl": -494.49,
      "pl_pct": -0.99,
      "sell_reason": "月RSI4=50<77"
    },
    {
      "ticker": "035590",
      "buy_date": "2011-05-05",
      "buy_price": 0.23,
      "sell_date": "2011-05-06",
      "sell_price": 0.33,
      "shares": 217391,
      "pl": 21739.1,
      "pl_pct": 43.48,
      "sell_reason": "月RSI4=50<77"
    },
    {
      "ticker": "037899",
      "buy_date": "2011-05-05",
      "buy_price": 0.6,
      "sell_date": "2011-05-06",
      "sell_price": 0.53,
      "shares": 83333,
      "pl": -5833.31,
      "pl_pct": -11.67,
      "sell_reason": "止損-11.7%"
    },
    {
      "ticker": "034781",
      "buy_date": "2011-05-06",
      "buy_price": 1.79,
      "sell_date": "2011-05-09",
      "sell_price": 1.95,
      "shares": 27932,
      "pl": 4469.12,
      "pl_pct": 8.94,
      "sell_reason": "月RSI4=50<77"
    },
    {
      "ticker": "3607",
      "buy_date": "2011-05-06",
      "buy_price": 58.9,
      "sell_date": "2011-05-09",
      "sell_price": 58.9,
      "shares": 848,
      "pl": 0.0,
      "pl_pct": 0.0,
      "sell_reason": "月RSI4=50<77"
    },
    {
      "ticker": "037278",
      "buy_date": "2011-05-06",
      "buy_price": 0.28,
      "sell_date": "2011-05-09",
      "sell_price": 0.32,
      "shares": 178571,
      "pl": 7142.84,
      "pl_pct": 14.29,
      "sell_reason": "月RSI4=50<77"
    },
    {
      "ticker": "037380",
      "buy_date": "2011-05-06",
      "buy_price": 0.43,
      "sell_date": "2011-05-09",
      "sell_price": 0.48,
      "shares": 116279,
      "pl": 5813.95,
      "pl_pct": 11.63,
      "sell_reason": "月RSI4=50<77"
    },
    {
      "ticker": "035590",
      "buy_date": "2011-05-06",
      "buy_price": 0.33,
      "sell_date": "2011-05-09",
      "sell_price": 0.48,
      "shares": 151515,
      "pl": 22727.25,
      "pl_pct": 45.45,
      "sell_reason": "月RSI4=50<77"
    },
    {
      "ticker": "035301",
      "buy_date": "2011-05-09",
      "buy_price": 0.88,
      "sell_date": "2011-05-10",
      "sell_price": 0.74,
      "shares": 56818,
      "pl": -7954.52,
      "pl_pct": -15.91,
      "sell_reason": "止損-15.9%"
    },
    {
      "ticker": "035612",
      "buy_date": "2011-05-09",
      "buy_price": 0.87,
      "sell_date": "2011-05-10",
      "sell_price": 0.83,
      "shares": 57471,
      "pl": -2298.84,
      "pl_pct": -4.6,
      "sell_reason": "月RSI4=50<77"
    },
    {
      "ticker": "034781",
      "buy_date": "2011-05-09",
      "buy_price": 1.95,
      "sell_date": "2011-05-10",
      "sell_price": 1.8,
      "shares": 25641,
      "pl": -3846.15,
      "pl_pct": -7.69,
      "sell_reason": "月RSI4=50<77"
    },
    {
      "ticker": "037298",
      "buy_date": "2011-05-09",
      "buy_price": 1.52,
      "sell_date": "2011-05-10",
      "sell_price": 1.48,
      "shares": 32894,
      "pl": -1315.76,
      "pl_pct": -2.63,
      "sell_reason": "月RSI4=50<77"
    },
    {
      "ticker": "035590",
      "buy_date": "2011-05-09",
      "buy_price": 0.48,
      "sell_date": "2011-05-10",
      "sell_price": 0.42,
      "shares": 104166,
      "pl": -6249.96,
      "pl_pct": -12.5,
      "sell_reason": "止損-12.5%"
    },
    {
      "ticker": "036644",
      "buy_date": "2011-05-10",
      "buy_price": 0.44,
      "sell_date": "2011-05-11",
      "sell_price": 0.45,
      "shares": 113636,
      "pl": 1136.36,
      "pl_pct": 2.27,
      "sell_reason": "月RSI4=50<77"
    },
    {
      "ticker": "035192",
      "buy_date": "2011-05-10",
      "buy_price": 0.8,
      "sell_date": "2011-05-11",
      "sell_price": 0.64,
      "shares": 62499,
      "pl": -9999.84,
      "pl_pct": -20.0,
      "sell_reason": "止損-20.0%"
    },
    {
      "ticker": "038951",
      "buy_date": "2011-05-10",
      "buy_price": 3.35,
      "sell_date": "2011-05-11",
      "sell_price": 3.19,
      "shares": 14925,
      "pl": -2388.0,
      "pl_pct": -4.78,
      "sell_reason": "月RSI4=50<77"
    },
    {
      "ticker": "037182",
      "buy_date": "2011-05-10",
      "buy_price": 0.54,
      "sell_date": "2011-05-11",
      "sell_price": 0.57,
      "shares": 92592,
      "pl": 2777.76,
      "pl_pct": 5.56,
      "sell_reason": "月RSI4=50<77"
    },
    {
      "ticker": "037415",
      "buy_date": "2011-05-10",
      "buy_price": 1.21,
      "sell_date": "2011-05-11",
      "sell_price": 1.35,
      "shares": 41322,
      "pl": 5785.08,
      "pl_pct": 11.57,
      "sell_reason": "月RSI4=50<77"
    },
    {
      "ticker": "035301",
      "buy_date": "2011-05-11",
      "buy_price": 0.93,
      "sell_date": "2011-05-12",
      "sell_price": 0.89,
      "shares": 53763,
      "pl": -2150.52,
      "pl_pct": -4.3,
      "sell_reason": "月RSI4=50<77"
    },
    {
      "ticker": "4104",
      "buy_date": "2011-05-11",
      "buy_price": 94.6,
      "sell_date": "2011-05-12",
      "sell_price": 93.14,
      "shares": 528,
      "pl": -774.04,
      "pl_pct": -1.55,
      "sell_reason": "月RSI4=50<77"
    },
    {
      "ticker": "038027",
      "buy_date": "2011-05-11",
      "buy_price": 0.77,
      "sell_date": "2011-05-12",
      "sell_price": 0.76,
      "shares": 64935,
      "pl": -649.35,
      "pl_pct": -1.3,
      "sell_reason": "月RSI4=50<77"
    },
    {
      "ticker": "037221",
      "buy_date": "2011-05-11",
      "buy_price": 1.01,
      "sell_date": "2011-05-12",
      "sell_price": 0.92,
      "shares": 49504,
      "pl": -4455.36,
      "pl_pct": -8.91,
      "sell_reason": "月RSI4=50<77"
    },
    {
      "ticker": "036786",
      "buy_date": "2011-05-11",
      "buy_price": 0.36,
      "sell_date": "2011-05-12",
      "sell_price": 0.38,
      "shares": 138888,
      "pl": 2777.76,
      "pl_pct": 5.56,
      "sell_reason": "月RSI4=50<77"
    },
    {
      "ticker": "036644",
      "buy_date": "2011-05-12",
      "buy_price": 0.55,
      "sell_date": "2011-05-13",
      "sell_price": 0.5,
      "shares": 90909,
      "pl": -4545.45,
      "pl_pct": -9.09,
      "sell_reason": "止損-9.1%"
    },
    {
      "ticker": "035830",
      "buy_date": "2011-05-12",
      "buy_price": 0.94,
      "sell_date": "2011-05-13",
      "sell_price": 0.96,
      "shares": 53191,
      "pl": 1063.82,
      "pl_pct": 2.13,
      "sell_reason": "月RSI4=50<77"
    },
    {
      "ticker": "037574",
      "buy_date": "2011-05-12",
      "buy_price": 5.8,
      "sell_date": "2011-05-13",
      "sell_price": 4.9,
      "shares": 8620,
      "pl": -7758.0,
      "pl_pct": -15.52,
      "sell_reason": "止損-15.5%"
    },
    {
      "ticker": "04035P",
      "buy_date": "2011-05-12",
      "buy_price": 1.13,
      "sell_date": "2011-05-13",
      "sell_price": 1.15,
      "shares": 44247,
      "pl": 884.94,
      "pl_pct": 1.77,
      "sell_reason": "月RSI4=50<77"
    },
    {
      "ticker": "04203P",
      "buy_date": "2011-05-12",
      "buy_price": 1.34,
      "sell_date": "2011-05-13",
      "sell_price": 1.41,
      "shares": 37313,
      "pl": 2611.91,
      "pl_pct": 5.22,
      "sell_reason": "月RSI4=50<77"
    },
    {
      "ticker": "038446",
      "buy_date": "2011-05-31",
      "buy_price": 1.73,
      "sell_date": "2011-06-01",
      "sell_price": 2.04,
      "shares": 28901,
      "pl": 8959.31,
      "pl_pct": 17.92,
      "sell_reason": "月RSI4=50<77"
    },
    {
      "ticker": "037770",
      "buy_date": "2011-05-31",
      "buy_price": 0.39,
      "sell_date": "2011-06-01",
      "sell_price": 0.44,
      "shares": 128205,
      "pl": 6410.25,
      "pl_pct": 12.82,
      "sell_reason": "月RSI4=50<77"
    },
    {
      "ticker": "039181",
      "buy_date": "2011-05-31",
      "buy_price": 2.61,
      "sell_date": "2011-06-01",
      "sell_price": 2.63,
      "shares": 19157,
      "pl": 383.14,
      "pl_pct": 0.77,
      "sell_reason": "月RSI4=50<77"
    },
    {
      "ticker": "039623",
      "buy_date": "2011-05-31",
      "buy_price": 4.63,
      "sell_date": "2011-06-01",
      "sell_price": 4.97,
      "shares": 10799,
      "pl": 3671.66,
      "pl_pct": 7.34,
      "sell_reason": "月RSI4=50<77"
    },
    {
      "ticker": "1434",
      "buy_date": "2011-06-01",
      "buy_price": 29.5,
      "sell_date": "2011-06-02",
      "sell_price": 29.5,
      "shares": 1695,
      "pl": 0.0,
      "pl_pct": 0.0,
      "sell_reason": "月RSI4=50<77"
    },
    {
      "ticker": "035900",
      "buy_date": "2011-06-01",
      "buy_price": 0.73,
      "sell_date": "2011-06-02",
      "sell_price": 0.56,
      "shares": 68493,
      "pl": -11643.81,
      "pl_pct": -23.29,
      "sell_reason": "止損-23.3%"
    },
    {
      "ticker": "035303",
      "buy_date": "2011-06-01",
      "buy_price": 0.1,
      "sell_date": "2011-06-02",
      "sell_price": 0.04,
      "shares": 499999,
      "pl": -29999.94,
      "pl_pct": -60.0,
      "sell_reason": "止損-60.0%"
    },
    {
      "ticker": "040526",
      "buy_date": "2011-06-01",
      "buy_price": 1.17,
      "sell_date": "2011-06-02",
      "sell_price": 0.97,
      "shares": 42735,
      "pl": -8547.0,
      "pl_pct": -17.09,
      "sell_reason": "止損-17.1%"
    },
    {
      "ticker": "037610",
      "buy_date": "2011-06-02",
      "buy_price": 0.6,
      "sell_date": "2011-06-03",
      "sell_price": 0.66,
      "shares": 83333,
      "pl": 4999.98,
      "pl_pct": 10.0,
      "sell_reason": "月RSI4=50<77"
    },
    {
      "ticker": "038609",
      "buy_date": "2011-06-02",
      "buy_price": 1.65,
      "sell_date": "2011-06-03",
      "sell_price": 1.76,
      "shares": 30303,
      "pl": 3333.33,
      "pl_pct": 6.67,
      "sell_reason": "月RSI4=50<77"
    },
    {
      "ticker": "035970",
      "buy_date": "2011-06-02",
      "buy_price": 0.83,
      "sell_date": "2011-06-03",
      "sell_price": 0.9,
      "shares": 60240,
      "pl": 4216.8,
      "pl_pct": 8.43,
      "sell_reason": "月RSI4=50<77"
    },
    {
      "ticker": "039388",
      "buy_date": "2011-06-02",
      "buy_price": 1.4,
      "sell_date": "2011-06-03",
      "sell_price": 1.49,
      "shares": 35714,
      "pl": 3214.26,
      "pl_pct": 6.43,
      "sell_reason": "月RSI4=50<77"
    },
    {
      "ticker": "036917",
      "buy_date": "2011-05-31",
      "buy_price": 2.15,
      "sell_date": "2011-06-07",
      "sell_price": 2.17,
      "shares": 23255,
      "pl": 465.1,
      "pl_pct": 0.93,
      "sell_reason": "月RSI4=50<77"
    },
    {
      "ticker": "037211",
      "buy_date": "2011-06-03",
      "buy_price": 0.15,
      "sell_date": "2011-06-07",
      "sell_price": 0.12,
      "shares": 333333,
      "pl": -9999.99,
      "pl_pct": -20.0,
      "sell_reason": "止損-20.0%"
    },
    {
      "ticker": "035970",
      "buy_date": "2011-06-03",
      "buy_price": 0.9,
      "sell_date": "2011-06-07",
      "sell_price": 0.85,
      "shares": 55555,
      "pl": -2777.75,
      "pl_pct": -5.56,
      "sell_reason": "月RSI4=50<77"
    },
    {
      "ticker": "038998",
      "buy_date": "2011-06-03",
      "buy_price": 1.17,
      "sell_date": "2011-06-07",
      "sell_price": 1.33,
      "shares": 42735,
      "pl": 6837.6,
      "pl_pct": 13.68,
      "sell_reason": "月RSI4=50<77"
    },
    {
      "ticker": "039056",
      "buy_date": "2011-06-03",
      "buy_price": 1.96,
      "sell_date": "2011-06-07",
      "sell_price": 2.22,
      "shares": 25510,
      "pl": 6632.6,
      "pl_pct": 13.27,
      "sell_reason": "月RSI4=50<77"
    },
    {
      "ticker": "4938",
      "buy_date": "2011-06-03",
      "buy_price": 31.8,
      "sell_date": "2011-06-07",
      "sell_price": 31.2,
      "shares": 1572,
      "pl": -943.2,
      "pl_pct": -1.89,
      "sell_reason": "月RSI4=50<77"
    },
    {
      "ticker": "038681",
      "buy_date": "2011-06-07",
      "buy_price": 2.33,
      "sell_date": "2011-06-08",
      "sell_price": 2.35,
      "shares": 21459,
      "pl": 429.18,
      "pl_pct": 0.86,
      "sell_reason": "月RSI4=50<77"
    },
    {
      "ticker": "039216",
      "buy_date": "2011-06-07",
      "buy_price": 1.08,
      "sell_date": "2011-06-08",
      "sell_price": 1.15,
      "shares": 46296,
      "pl": 3240.72,
      "pl_pct": 6.48,
      "sell_reason": "月RSI4=50<77"
    },
    {
      "ticker": "037388",
      "buy_date": "2011-06-07",
      "buy_price": 1.86,
      "sell_date": "2011-06-08",
      "sell_price": 1.86,
      "shares": 26881,
      "pl": 0.0,
      "pl_pct": 0.0,
      "sell_reason": "月RSI4=50<77"
    },
    {
      "ticker": "038611",
      "buy_date": "2011-06-07",
      "buy_price": 1.38,
      "sell_date": "2011-06-08",
      "sell_price": 1.28,
      "shares": 36231,
      "pl": -3623.1,
      "pl_pct": -7.25,
      "sell_reason": "月RSI4=50<77"
    },
    {
      "ticker": "04316P",
      "buy_date": "2011-06-07",
      "buy_price": 1.57,
      "sell_date": "2011-06-08",
      "sell_price": 1.53,
      "shares": 31847,
      "pl": -1273.88,
      "pl_pct": -2.55,
      "sell_reason": "月RSI4=50<77"
    },
    {
      "ticker": "036990",
      "buy_date": "2011-06-08",
      "buy_price": 0.26,
      "sell_date": "2011-06-09",
      "sell_price": 0.23,
      "shares": 192307,
      "pl": -5769.21,
      "pl_pct": -11.54,
      "sell_reason": "止損-11.5%"
    },
    {
      "ticker": "036726",
      "buy_date": "2011-06-08",
      "buy_price": 0.5,
      "sell_date": "2011-06-09",
      "sell_price": 0.47,
      "shares": 100000,
      "pl": -3000.0,
      "pl_pct": -6.0,
      "sell_reason": "月RSI4=50<77"
    },
    {
      "ticker": "039216",
      "buy_date": "2011-06-08",
      "buy_price": 1.15,
      "sell_date": "2011-06-09",
      "sell_price": 1.09,
      "shares": 43478,
      "pl": -2608.68,
      "pl_pct": -5.22,
      "sell_reason": "月RSI4=50<77"
    },
    {
      "ticker": "040617",
      "buy_date": "2011-06-08",
      "buy_price": 2.79,
      "sell_date": "2011-06-09",
      "sell_price": 2.61,
      "shares": 17921,
      "pl": -3225.78,
      "pl_pct": -6.45,
      "sell_reason": "月RSI4=50<77"
    },
    {
      "ticker": "038943",
      "buy_date": "2011-06-08",
      "buy_price": 2.82,
      "sell_date": "2011-06-09",
      "sell_price": 2.66,
      "shares": 17730,
      "pl": -2836.8,
      "pl_pct": -5.67,
      "sell_reason": "月RSI4=50<77"
    },
    {
      "ticker": "038319",
      "buy_date": "2011-06-02",
      "buy_price": 0.36,
      "sell_date": "2011-06-10",
      "sell_price": 0.2,
      "shares": 138888,
      "pl": -22222.08,
      "pl_pct": -44.44,
      "sell_reason": "止損-44.4%"
    },
    {
      "ticker": "04158P",
      "buy_date": "2011-06-09",
      "buy_price": 1.4,
      "sell_date": "2011-06-10",
      "sell_price": 1.46,
      "shares": 35714,
      "pl": 2142.84,
      "pl_pct": 4.29,
      "sell_reason": "月RSI4=50<77"
    },
    {
      "ticker": "8046",
      "buy_date": "2011-06-09",
      "buy_price": 114.58,
      "sell_date": "2011-06-10",
      "sell_price": 111.67,
      "shares": 436,
      "pl": -1270.07,
      "pl_pct": -2.54,
      "sell_reason": "月RSI4=50<77"
    },
    {
      "ticker": "04326P",
      "buy_date": "2011-06-09",
      "buy_price": 1.21,
      "sell_date": "2011-06-10",
      "sell_price": 1.24,
      "shares": 41322,
      "pl": 1239.66,
      "pl_pct": 2.48,
      "sell_reason": "月RSI4=50<77"
    },
    {
      "ticker": "2520",
      "buy_date": "2011-06-09",
      "buy_price": 25.2,
      "sell_date": "2011-06-10",
      "sell_price": 24.4,
      "shares": 1984,
      "pl": -1587.2,
      "pl_pct": -3.17,
      "sell_reason": "月RSI4=50<77"
    },
    {
      "ticker": "036007",
      "buy_date": "2011-06-09",
      "buy_price": 0.05,
      "sell_date": "2011-06-10",
      "sell_price": 0.04,
      "shares": 999999,
      "pl": -9999.99,
      "pl_pct": -20.0,
      "sell_reason": "止損-20.0%"
    },
    {
      "ticker": "036560",
      "buy_date": "2011-06-01",
      "buy_price": 6.2,
      "sell_date": "2011-06-22",
      "sell_price": 4.36,
      "shares": 8064,
      "pl": -14837.76,
      "pl_pct": -29.68,
      "sell_reason": "止損-29.7%"
    },
    {
      "ticker": "040822",
      "buy_date": "2011-07-21",
      "buy_price": 0.31,
      "sell_date": "2011-07-22",
      "sell_price": 0.3,
      "shares": 161290,
      "pl": -1612.9,
      "pl_pct": -3.23,
      "sell_reason": "月RSI4=50<77"
    },
    {
      "ticker": "041536",
      "buy_date": "2011-07-21",
      "buy_price": 1.55,
      "sell_date": "2011-07-22",
      "sell_price": 1.57,
      "shares": 32258,
      "pl": 645.16,
      "pl_pct": 1.29,
      "sell_reason": "月RSI4=50<77"
    },
    {
      "ticker": "038709",
      "buy_date": "2011-07-21",
      "buy_price": 1.71,
      "sell_date": "2011-07-22",
      "sell_price": 1.76,
      "shares": 29239,
      "pl": 1461.95,
      "pl_pct": 2.92,
      "sell_reason": "月RSI4=50<77"
    },
    {
      "ticker": "038994",
      "buy_date": "2011-07-21",
      "buy_price": 0.94,
      "sell_date": "2011-07-22",
      "sell_price": 0.88,
      "shares": 53191,
      "pl": -3191.46,
      "pl_pct": -6.38,
      "sell_reason": "月RSI4=50<77"
    },
    {
      "ticker": "039816",
      "buy_date": "2011-07-21",
      "buy_price": 2.97,
      "sell_date": "2011-07-22",
      "sell_price": 3.59,
      "shares": 16835,
      "pl": 10437.7,
      "pl_pct": 20.88,
      "sell_reason": "月RSI4=50<77"
    },
    {
      "ticker": "039999",
      "buy_date": "2011-07-22",
      "buy_price": 3.22,
      "sell_date": "2011-07-25",
      "sell_price": 3.3,
      "shares": 15527,
      "pl": 1242.16,
      "pl_pct": 2.48,
      "sell_reason": "月RSI4=50<77"
    },
    {
      "ticker": "042229",
      "buy_date": "2011-07-22",
      "buy_price": 2.85,
      "sell_date": "2011-07-25",
      "sell_price": 2.92,
      "shares": 17543,
      "pl": 1228.01,
      "pl_pct": 2.46,
      "sell_reason": "月RSI4=50<77"
    },
    {
      "ticker": "038999",
      "buy_date": "2011-07-22",
      "buy_price": 0.89,
      "sell_date": "2011-07-25",
      "sell_price": 0.72,
      "shares": 56179,
      "pl": -9550.43,
      "pl_pct": -19.1,
      "sell_reason": "止損-19.1%"
    },
    {
      "ticker": "040565",
      "buy_date": "2011-07-22",
      "buy_price": 1.77,
      "sell_date": "2011-07-25",
      "sell_price": 1.84,
      "shares": 28248,
      "pl": 1977.36,
      "pl_pct": 3.95,
      "sell_reason": "月RSI4=50<77"
    },
    {
      "ticker": "041009",
      "buy_date": "2011-07-22",
      "buy_price": 0.51,
      "sell_date": "2011-07-25",
      "sell_price": 0.46,
      "shares": 98039,
      "pl": -4901.95,
      "pl_pct": -9.8,
      "sell_reason": "月RSI4=50<77"
    },
    {
      "ticker": "038089",
      "buy_date": "2011-07-25",
      "buy_price": 0.45,
      "sell_date": "2011-07-26",
      "sell_price": 0.42,
      "shares": 111111,
      "pl": -3333.33,
      "pl_pct": -6.67,
      "sell_reason": "月RSI4=50<77"
    },
    {
      "ticker": "04255P",
      "buy_date": "2011-07-25",
      "buy_price": 1.37,
      "sell_date": "2011-07-26",
      "sell_price": 1.23,
      "shares": 36496,
      "pl": -5109.44,
      "pl_pct": -10.22,
      "sell_reason": "止損-10.2%"
    },
    {
      "ticker": "041786",
      "buy_date": "2011-07-25",
      "buy_price": 1.51,
      "sell_date": "2011-07-26",
      "sell_price": 1.53,
      "shares": 33112,
      "pl": 662.24,
      "pl_pct": 1.32,
      "sell_reason": "月RSI4=50<77"
    },
    {
      "ticker": "040466",
      "buy_date": "2011-07-25",
      "buy_price": 1.65,
      "sell_date": "2011-07-26",
      "sell_price": 1.53,
      "shares": 30303,
      "pl": -3636.36,
      "pl_pct": -7.27,
      "sell_reason": "月RSI4=50<77"
    },
    {
      "ticker": "037397",
      "buy_date": "2011-07-25",
      "buy_price": 0.34,
      "sell_date": "2011-07-27",
      "sell_price": 0.69,
      "shares": 147058,
      "pl": 51470.3,
      "pl_pct": 102.94,
      "sell_reason": "月RSI4=50<77"
    },
    {
      "ticker": "040616",
      "buy_date": "2011-07-26",
      "buy_price": 0.91,
      "sell_date": "2011-07-27",
      "sell_price": 1.14,
      "shares": 54945,
      "pl": 12637.35,
      "pl_pct": 25.27,
      "sell_reason": "月RSI4=50<77"
    },
    {
      "ticker": "040920",
      "buy_date": "2011-07-26",
      "buy_price": 1.01,
      "sell_date": "2011-07-27",
      "sell_price": 1.02,
      "shares": 49504,
      "pl": 495.04,
      "pl_pct": 0.99,
      "sell_reason": "月RSI4=50<77"
    },
    {
      "ticker": "040820",
      "buy_date": "2011-07-26",
      "buy_price": 0.41,
      "sell_date": "2011-07-27",
      "sell_price": 0.36,
      "shares": 121951,
      "pl": -6097.55,
      "pl_pct": -12.2,
      "sell_reason": "止損-12.2%"
    },
    {
      "ticker": "038987",
      "buy_date": "2011-07-26",
      "buy_price": 1.61,
      "sell_date": "2011-07-28",
      "sell_price": 1.47,
      "shares": 31055,
      "pl": -4347.7,
      "pl_pct": -8.7,
      "sell_reason": "月RSI4=50<77"
    },
    {
      "ticker": "038790",
      "buy_date": "2011-07-27",
      "buy_price": 1.66,
      "sell_date": "2011-07-28",
      "sell_price": 1.69,
      "shares": 30120,
      "pl": 903.6,
      "pl_pct": 1.81,
      "sell_reason": "月RSI4=50<77"
    },
    {
      "ticker": "040270",
      "buy_date": "2011-07-27",
      "buy_price": 1.61,
      "sell_date": "2011-07-28",
      "sell_price": 1.55,
      "shares": 31055,
      "pl": -1863.3,
      "pl_pct": -3.73,
      "sell_reason": "月RSI4=50<77"
    },
    {
      "ticker": "040616",
      "buy_date": "2011-07-27",
      "buy_price": 1.14,
      "sell_date": "2011-07-28",
      "sell_price": 1.07,
      "shares": 43859,
      "pl": -3070.13,
      "pl_pct": -6.14,
      "sell_reason": "月RSI4=50<77"
    },
    {
      "ticker": "041551",
      "buy_date": "2011-07-27",
      "buy_price": 0.68,
      "sell_date": "2011-07-28",
      "sell_price": 0.68,
      "shares": 73529,
      "pl": 0.0,
      "pl_pct": 0.0,
      "sell_reason": "月RSI4=50<77"
    },
    {
      "ticker": "041295",
      "buy_date": "2011-07-27",
      "buy_price": 2.28,
      "sell_date": "2011-07-28",
      "sell_price": 1.82,
      "shares": 21929,
      "pl": -10087.34,
      "pl_pct": -20.18,
      "sell_reason": "止損-20.2%"
    },
    {
      "ticker": "040360",
      "buy_date": "2011-07-26",
      "buy_price": 4.13,
      "sell_date": "2011-07-29",
      "sell_price": 4.54,
      "shares": 12106,
      "pl": 4963.46,
      "pl_pct": 9.93,
      "sell_reason": "月RSI4=50<77"
    },
    {
      "ticker": "038790",
      "buy_date": "2011-07-28",
      "buy_price": 1.69,
      "sell_date": "2011-07-29",
      "sell_price": 1.67,
      "shares": 29585,
      "pl": -591.7,
      "pl_pct": -1.18,
      "sell_reason": "月RSI4=50<77"
    },
    {
      "ticker": "040888",
      "buy_date": "2011-07-28",
      "buy_price": 0.46,
      "sell_date": "2011-07-29",
      "sell_price": 0.49,
      "shares": 108695,
      "pl": 3260.85,
      "pl_pct": 6.52,
      "sell_reason": "月RSI4=50<77"
    },
    {
      "ticker": "041993",
      "buy_date": "2011-07-28",
      "buy_price": 1.68,
      "sell_date": "2011-07-29",
      "sell_price": 1.57,
      "shares": 29761,
      "pl": -3273.71,
      "pl_pct": -6.55,
      "sell_reason": "月RSI4=50<77"
    },
    {
      "ticker": "040181",
      "buy_date": "2011-07-28",
      "buy_price": 1.06,
      "sell_date": "2011-07-29",
      "sell_price": 1.15,
      "shares": 47169,
      "pl": 4245.21,
      "pl_pct": 8.49,
      "sell_reason": "月RSI4=50<77"
    },
    {
      "ticker": "040751",
      "buy_date": "2011-07-28",
      "buy_price": 0.6,
      "sell_date": "2011-07-29",
      "sell_price": 0.55,
      "shares": 83333,
      "pl": -4166.65,
      "pl_pct": -8.33,
      "sell_reason": "止損-8.3%"
    },
    {
      "ticker": "2013",
      "buy_date": "2011-08-01",
      "buy_price": 28.15,
      "sell_date": "2011-08-02",
      "sell_price": 28.25,
      "shares": 1776,
      "pl": 177.6,
      "pl_pct": 0.36,
      "sell_reason": "月RSI4=50<77"
    },
    {
      "ticker": "038389",
      "buy_date": "2011-08-01",
      "buy_price": 0.64,
      "sell_date": "2011-08-02",
      "sell_price": 0.55,
      "shares": 78125,
      "pl": -7031.25,
      "pl_pct": -14.06,
      "sell_reason": "止損-14.1%"
    },
    {
      "ticker": "038711",
      "buy_date": "2011-08-01",
      "buy_price": 2.17,
      "sell_date": "2011-08-02",
      "sell_price": 1.88,
      "shares": 23041,
      "pl": -6681.89,
      "pl_pct": -13.36,
      "sell_reason": "止損-13.4%"
    },
    {
      "ticker": "040013",
      "buy_date": "2011-08-01",
      "buy_price": 1.82,
      "sell_date": "2011-08-02",
      "sell_price": 1.89,
      "shares": 27472,
      "pl": 1923.04,
      "pl_pct": 3.85,
      "sell_reason": "月RSI4=50<77"
    },
    {
      "ticker": "040865",
      "buy_date": "2011-08-01",
      "buy_price": 1.52,
      "sell_date": "2011-08-02",
      "sell_price": 1.44,
      "shares": 32894,
      "pl": -2631.52,
      "pl_pct": -5.26,
      "sell_reason": "月RSI4=50<77"
    },
    {
      "ticker": "042340",
      "buy_date": "2011-09-16",
      "buy_price": 1.4,
      "sell_date": "2011-09-19",
      "sell_price": 1.35,
      "shares": 35714,
      "pl": -1785.7,
      "pl_pct": -3.57,
      "sell_reason": "月RSI4=50<77"
    },
    {
      "ticker": "041863",
      "buy_date": "2011-09-16",
      "buy_price": 0.72,
      "sell_date": "2011-09-19",
      "sell_price": 0.74,
      "shares": 69444,
      "pl": 1388.88,
      "pl_pct": 2.78,
      "sell_reason": "月RSI4=50<77"
    },
    {
      "ticker": "2458",
      "buy_date": "2011-09-16",
      "buy_price": 29.9,
      "sell_date": "2011-09-19",
      "sell_price": 29.5,
      "shares": 1672,
      "pl": -668.8,
      "pl_pct": -1.34,
      "sell_reason": "月RSI4=50<77"
    },
    {
      "ticker": "3046",
      "buy_date": "2011-09-16",
      "buy_price": 7.37,
      "sell_date": "2011-09-19",
      "sell_price": 7.15,
      "shares": 6784,
      "pl": -1492.48,
      "pl_pct": -2.99,
      "sell_reason": "月RSI4=50<77"
    },
    {
      "ticker": "04529P",
      "buy_date": "2011-09-19",
      "buy_price": 0.45,
      "sell_date": "2011-09-20",
      "sell_price": 0.47,
      "shares": 111111,
      "pl": 2222.22,
      "pl_pct": 4.44,
      "sell_reason": "月RSI4=50<77"
    },
    {
      "ticker": "2439",
      "buy_date": "2011-09-19",
      "buy_price": 31.25,
      "sell_date": "2011-09-20",
      "sell_price": 31.3,
      "shares": 1600,
      "pl": 80.0,
      "pl_pct": 0.16,
      "sell_reason": "月RSI4=50<77"
    },
    {
      "ticker": "041863",
      "buy_date": "2011-09-19",
      "buy_price": 0.74,
      "sell_date": "2011-09-20",
      "sell_price": 0.77,
      "shares": 67567,
      "pl": 2027.01,
      "pl_pct": 4.05,
      "sell_reason": "月RSI4=50<77"
    },
    {
      "ticker": "1516",
      "buy_date": "2011-09-19",
      "buy_price": 6.15,
      "sell_date": "2011-09-20",
      "sell_price": 6.15,
      "shares": 8130,
      "pl": 0.0,
      "pl_pct": 0.0,
      "sell_reason": "月RSI4=50<77"
    },
    {
      "ticker": "040387",
      "buy_date": "2011-09-19",
      "buy_price": 0.22,
      "sell_date": "2011-09-20",
      "sell_price": 0.2,
      "shares": 227272,
      "pl": -4545.44,
      "pl_pct": -9.09,
      "sell_reason": "月RSI4=50<77"
    },
    {
      "ticker": "042223",
      "buy_date": "2011-09-20",
      "buy_price": 9.5,
      "sell_date": "2011-09-21",
      "sell_price": 11.9,
      "shares": 5263,
      "pl": 12631.2,
      "pl_pct": 25.26,
      "sell_reason": "月RSI4=50<77"
    },
    {
      "ticker": "04529P",
      "buy_date": "2011-09-20",
      "buy_price": 0.47,
      "sell_date": "2011-09-21",
      "sell_price": 0.5,
      "shares": 106382,
      "pl": 3191.46,
      "pl_pct": 6.38,
      "sell_reason": "月RSI4=50<77"
    },
    {
      "ticker": "041863",
      "buy_date": "2011-09-20",
      "buy_price": 0.77,
      "sell_date": "2011-09-21",
      "sell_price": 0.7,
      "shares": 64935,
      "pl": -4545.45,
      "pl_pct": -9.09,
      "sell_reason": "月RSI4=50<77"
    },
    {
      "ticker": "04590P",
      "buy_date": "2011-09-20",
      "buy_price": 2.0,
      "sell_date": "2011-09-21",
      "sell_price": 1.88,
      "shares": 25000,
      "pl": -3000.0,
      "pl_pct": -6.0,
      "sell_reason": "月RSI4=50<77"
    },
    {
      "ticker": "2439",
      "buy_date": "2011-09-20",
      "buy_price": 31.3,
      "sell_date": "2011-09-21",
      "sell_price": 31.4,
      "shares": 1597,
      "pl": 159.7,
      "pl_pct": 0.32,
      "sell_reason": "月RSI4=50<77"
    },
    {
      "ticker": "04421P",
      "buy_date": "2011-09-21",
      "buy_price": 0.95,
      "sell_date": "2011-09-22",
      "sell_price": 1.35,
      "shares": 52631,
      "pl": 21052.4,
      "pl_pct": 42.11,
      "sell_reason": "月RSI4=50<77"
    },
    {
      "ticker": "04529P",
      "buy_date": "2011-09-21",
      "buy_price": 0.5,
      "sell_date": "2011-09-22",
      "sell_price": 0.64,
      "shares": 100000,
      "pl": 14000.0,
      "pl_pct": 28.0,
      "sell_reason": "月RSI4=50<77"
    },
    {
      "ticker": "04267P",
      "buy_date": "2011-09-21",
      "buy_price": 0.92,
      "sell_date": "2011-09-22",
      "sell_price": 1.06,
      "shares": 54347,
      "pl": 7608.58,
      "pl_pct": 15.22,
      "sell_reason": "月RSI4=50<77"
    },
    {
      "ticker": "2352",
      "buy_date": "2011-09-21",
      "buy_price": 8.7,
      "sell_date": "2011-09-22",
      "sell_price": 8.25,
      "shares": 5747,
      "pl": -2586.15,
      "pl_pct": -5.17,
      "sell_reason": "月RSI4=50<77"
    },
    {
      "ticker": "042958",
      "buy_date": "2011-09-21",
      "buy_price": 0.49,
      "sell_date": "2011-09-22",
      "sell_price": 0.37,
      "shares": 102040,
      "pl": -12244.8,
      "pl_pct": -24.49,
      "sell_reason": "止損-24.5%"
    },
    {
      "ticker": "041919",
      "buy_date": "2011-09-16",
      "buy_price": 0.65,
      "sell_date": "2011-09-23",
      "sell_price": 0.5,
      "shares": 76923,
      "pl": -11538.45,
      "pl_pct": -23.08,
      "sell_reason": "止損-23.1%"
    },
    {
      "ticker": "5305",
      "buy_date": "2011-10-07",
      "buy_price": 18.4,
      "sell_date": "2011-10-11",
      "sell_price": 18.25,
      "shares": 2717,
      "pl": -407.55,
      "pl_pct": -0.82,
      "sell_reason": "月RSI4=50<77"
    },
    {
      "ticker": "5515",
      "buy_date": "2011-10-07",
      "buy_price": 14.7,
      "sell_date": "2011-10-11",
      "sell_price": 14.9,
      "shares": 3401,
      "pl": 680.2,
      "pl_pct": 1.36,
      "sell_reason": "月RSI4=50<77"
    },
    {
      "ticker": "04506P",
      "buy_date": "2011-10-07",
      "buy_price": 1.59,
      "sell_date": "2011-10-11",
      "sell_price": 1.49,
      "shares": 31446,
      "pl": -3144.6,
      "pl_pct": -6.29,
      "sell_reason": "月RSI4=50<77"
    },
    {
      "ticker": "2449",
      "buy_date": "2011-10-07",
      "buy_price": 11.25,
      "sell_date": "2011-10-11",
      "sell_price": 11.35,
      "shares": 4444,
      "pl": 444.4,
      "pl_pct": 0.89,
      "sell_reason": "月RSI4=50<77"
    },
    {
      "ticker": "042170",
      "buy_date": "2011-10-11",
      "buy_price": 2.91,
      "sell_date": "2011-10-12",
      "sell_price": 3.09,
      "shares": 17182,
      "pl": 3092.76,
      "pl_pct": 6.19,
      "sell_reason": "月RSI4=50<77"
    },
    {
      "ticker": "045104",
      "buy_date": "2011-10-11",
      "buy_price": 0.51,
      "sell_date": "2011-10-12",
      "sell_price": 0.43,
      "shares": 98039,
      "pl": -7843.12,
      "pl_pct": -15.69,
      "sell_reason": "止損-15.7%"
    },
    {
      "ticker": "042956",
      "buy_date": "2011-10-11",
      "buy_price": 1.77,
      "sell_date": "2011-10-12",
      "sell_price": 1.8,
      "shares": 28248,
      "pl": 847.44,
      "pl_pct": 1.69,
      "sell_reason": "月RSI4=50<77"
    },
    {
      "ticker": "044012",
      "buy_date": "2011-10-11",
      "buy_price": 0.26,
      "sell_date": "2011-10-12",
      "sell_price": 0.28,
      "shares": 192307,
      "pl": 3846.14,
      "pl_pct": 7.69,
      "sell_reason": "月RSI4=50<77"
    },
    {
      "ticker": "041716",
      "buy_date": "2011-10-07",
      "buy_price": 2.39,
      "sell_date": "2011-10-13",
      "sell_price": 2.0,
      "shares": 20920,
      "pl": -8158.8,
      "pl_pct": -16.32,
      "sell_reason": "止損-16.3%"
    },
    {
      "ticker": "041753",
      "buy_date": "2011-10-11",
      "buy_price": 0.98,
      "sell_date": "2011-10-13",
      "sell_price": 0.9,
      "shares": 51020,
      "pl": -4081.6,
      "pl_pct": -8.16,
      "sell_reason": "月RSI4=50<77"
    },
    {
      "ticker": "042596",
      "buy_date": "2011-10-12",
      "buy_price": 0.31,
      "sell_date": "2011-10-13",
      "sell_price": 0.33,
      "shares": 161290,
      "pl": 3225.8,
      "pl_pct": 6.45,
      "sell_reason": "月RSI4=50<77"
    },
    {
      "ticker": "043735",
      "buy_date": "2011-10-12",
      "buy_price": 0.57,
      "sell_date": "2011-10-13",
      "sell_price": 0.64,
      "shares": 87719,
      "pl": 6140.33,
      "pl_pct": 12.28,
      "sell_reason": "月RSI4=50<77"
    },
    {
      "ticker": "044242",
      "buy_date": "2011-10-12",
      "buy_price": 1.03,
      "sell_date": "2011-10-13",
      "sell_price": 1.11,
      "shares": 48543,
      "pl": 3883.44,
      "pl_pct": 7.77,
      "sell_reason": "月RSI4=50<77"
    },
    {
      "ticker": "044433",
      "buy_date": "2011-10-12",
      "buy_price": 1.12,
      "sell_date": "2011-10-13",
      "sell_price": 1.13,
      "shares": 44642,
      "pl": 446.42,
      "pl_pct": 0.89,
      "sell_reason": "月RSI4=50<77"
    },
    {
      "ticker": "044505",
      "buy_date": "2011-10-12",
      "buy_price": 1.33,
      "sell_date": "2011-10-13",
      "sell_price": 1.55,
      "shares": 37593,
      "pl": 8270.46,
      "pl_pct": 16.54,
      "sell_reason": "月RSI4=50<77"
    },
    {
      "ticker": "2704",
      "buy_date": "2011-10-13",
      "buy_price": 35.55,
      "sell_date": "2011-10-14",
      "sell_price": 34.8,
      "shares": 1406,
      "pl": -1054.5,
      "pl_pct": -2.11,
      "sell_reason": "月RSI4=50<77"
    },
    {
      "ticker": "040274",
      "buy_date": "2011-10-13",
      "buy_price": 5.05,
      "sell_date": "2011-10-14",
      "sell_price": 5.4,
      "shares": 9900,
      "pl": 3465.0,
      "pl_pct": 6.93,
      "sell_reason": "月RSI4=50<77"
    },
    {
      "ticker": "043735",
      "buy_date": "2011-10-13",
      "buy_price": 0.64,
      "sell_date": "2011-10-14",
      "sell_price": 0.47,
      "shares": 78125,
      "pl": -13281.25,
      "pl_pct": -26.56,
      "sell_reason": "止損-26.6%"
    },
    {
      "ticker": "043972",
      "buy_date": "2011-10-13",
      "buy_price": 0.63,
      "sell_date": "2011-10-14",
      "sell_price": 0.65,
      "shares": 79365,
      "pl": 1587.3,
      "pl_pct": 3.17,
      "sell_reason": "月RSI4=50<77"
    },
    {
      "ticker": "3356",
      "buy_date": "2011-10-14",
      "buy_price": 103.0,
      "sell_date": "2011-10-17",
      "sell_price": 103.0,
      "shares": 485,
      "pl": 0.0,
      "pl_pct": 0.0,
      "sell_reason": "月RSI4=50<77"
    },
    {
      "ticker": "040409",
      "buy_date": "2011-10-14",
      "buy_price": 1.05,
      "sell_date": "2011-10-17",
      "sell_price": 0.93,
      "shares": 47619,
      "pl": -5714.28,
      "pl_pct": -11.43,
      "sell_reason": "止損-11.4%"
    },
    {
      "ticker": "042536",
      "buy_date": "2011-10-14",
      "buy_price": 0.6,
      "sell_date": "2011-10-17",
      "sell_price": 0.51,
      "shares": 83333,
      "pl": -7499.97,
      "pl_pct": -15.0,
      "sell_reason": "止損-15.0%"
    },
    {
      "ticker": "042114",
      "buy_date": "2011-10-14",
      "buy_price": 3.49,
      "sell_date": "2011-10-17",
      "sell_price": 3.27,
      "shares": 14326,
      "pl": -3151.72,
      "pl_pct": -6.3,
      "sell_reason": "月RSI4=50<77"
    },
    {
      "ticker": "043505",
      "buy_date": "2011-10-14",
      "buy_price": 1.99,
      "sell_date": "2011-10-17",
      "sell_price": 2.23,
      "shares": 25125,
      "pl": 6030.0,
      "pl_pct": 12.06,
      "sell_reason": "月RSI4=50<77"
    },
    {
      "ticker": "043081",
      "buy_date": "2011-10-17",
      "buy_price": 0.53,
      "sell_date": "2011-10-18",
      "sell_price": 0.65,
      "shares": 94339,
      "pl": 11320.68,
      "pl_pct": 22.64,
      "sell_reason": "月RSI4=50<77"
    },
    {
      "ticker": "3494",
      "buy_date": "2011-10-17",
      "buy_price": 25.95,
      "sell_date": "2011-10-18",
      "sell_price": 25.65,
      "shares": 1926,
      "pl": -577.8,
      "pl_pct": -1.16,
      "sell_reason": "月RSI4=50<77"
    },
    {
      "ticker": "042435",
      "buy_date": "2011-10-17",
      "buy_price": 0.6,
      "sell_date": "2011-10-18",
      "sell_price": 0.5,
      "shares": 83333,
      "pl": -8333.3,
      "pl_pct": -16.67,
      "sell_reason": "止損-16.7%"
    },
    {
      "ticker": "6142",
      "buy_date": "2011-10-17",
      "buy_price": 8.96,
      "sell_date": "2011-10-18",
      "sell_price": 8.91,
      "shares": 5580,
      "pl": -279.0,
      "pl_pct": -0.56,
      "sell_reason": "月RSI4=50<77"
    },
    {
      "ticker": "044958",
      "buy_date": "2011-10-17",
      "buy_price": 2.52,
      "sell_date": "2011-10-18",
      "sell_price": 2.59,
      "shares": 19841,
      "pl": 1388.87,
      "pl_pct": 2.78,
      "sell_reason": "月RSI4=50<77"
    },
    {
      "ticker": "043076",
      "buy_date": "2011-10-13",
      "buy_price": 0.8,
      "sell_date": "2011-10-19",
      "sell_price": 0.9,
      "shares": 62499,
      "pl": 6249.9,
      "pl_pct": 12.5,
      "sell_reason": "月RSI4=50<77"
    },
    {
      "ticker": "044323",
      "buy_date": "2011-10-18",
      "buy_price": 0.75,
      "sell_date": "2011-10-19",
      "sell_price": 0.69,
      "shares": 66666,
      "pl": -3999.96,
      "pl_pct": -8.0,
      "sell_reason": "月RSI4=50<77"
    },
    {
      "ticker": "04878P",
      "buy_date": "2011-10-18",
      "buy_price": 3.17,
      "sell_date": "2011-10-19",
      "sell_price": 2.99,
      "shares": 15772,
      "pl": -2838.96,
      "pl_pct": -5.68,
      "sell_reason": "月RSI4=50<77"
    },
    {
      "ticker": "041997",
      "buy_date": "2011-10-18",
      "buy_price": 3.8,
      "sell_date": "2011-10-19",
      "sell_price": 3.06,
      "shares": 13157,
      "pl": -9736.18,
      "pl_pct": -19.47,
      "sell_reason": "止損-19.5%"
    },
    {
      "ticker": "044594",
      "buy_date": "2011-10-18",
      "buy_price": 2.89,
      "sell_date": "2011-10-19",
      "sell_price": 2.42,
      "shares": 17301,
      "pl": -8131.47,
      "pl_pct": -16.26,
      "sell_reason": "止損-16.3%"
    },
    {
      "ticker": "8163",
      "buy_date": "2011-10-18",
      "buy_price": 20.2,
      "sell_date": "2011-10-19",
      "sell_price": 19.85,
      "shares": 2475,
      "pl": -866.25,
      "pl_pct": -1.73,
      "sell_reason": "月RSI4=50<77"
    },
    {
      "ticker": "04859P",
      "buy_date": "2011-10-19",
      "buy_price": 1.88,
      "sell_date": "2011-10-20",
      "sell_price": 1.69,
      "shares": 26595,
      "pl": -5053.05,
      "pl_pct": -10.11,
      "sell_reason": "止損-10.1%"
    },
    {
      "ticker": "04819P",
      "buy_date": "2011-10-19",
      "buy_price": 1.75,
      "sell_date": "2011-10-20",
      "sell_price": 1.65,
      "shares": 28571,
      "pl": -2857.1,
      "pl_pct": -5.71,
      "sell_reason": "月RSI4=50<77"
    },
    {
      "ticker": "043223",
      "buy_date": "2011-10-19",
      "buy_price": 0.22,
      "sell_date": "2011-10-20",
      "sell_price": 0.13,
      "shares": 227272,
      "pl": -20454.48,
      "pl_pct": -40.91,
      "sell_reason": "止損-40.9%"
    },
    {
      "ticker": "04645P",
      "buy_date": "2011-10-19",
      "buy_price": 1.84,
      "sell_date": "2011-10-20",
      "sell_price": 1.76,
      "shares": 27173,
      "pl": -2173.84,
      "pl_pct": -4.35,
      "sell_reason": "月RSI4=50<77"
    },
    {
      "ticker": "045176",
      "buy_date": "2011-10-19",
      "buy_price": 0.97,
      "sell_date": "2011-10-20",
      "sell_price": 0.91,
      "shares": 51546,
      "pl": -3092.76,
      "pl_pct": -6.19,
      "sell_reason": "月RSI4=50<77"
    },
    {
      "ticker": "3356",
      "buy_date": "2011-10-24",
      "buy_price": 103.5,
      "sell_date": "2011-10-25",
      "sell_price": 102.5,
      "shares": 483,
      "pl": -483.0,
      "pl_pct": -0.97,
      "sell_reason": "月RSI4=50<77"
    },
    {
      "ticker": "3591",
      "buy_date": "2011-10-24",
      "buy_price": 72.0,
      "sell_date": "2011-10-25",
      "sell_price": 71.7,
      "shares": 694,
      "pl": -208.2,
      "pl_pct": -0.42,
      "sell_reason": "月RSI4=50<77"
    },
    {
      "ticker": "042738",
      "buy_date": "2011-10-24",
      "buy_price": 0.35,
      "sell_date": "2011-10-25",
      "sell_price": 0.35,
      "shares": 142857,
      "pl": 0.0,
      "pl_pct": 0.0,
      "sell_reason": "月RSI4=50<77"
    },
    {
      "ticker": "044315",
      "buy_date": "2011-10-24",
      "buy_price": 1.03,
      "sell_date": "2011-10-25",
      "sell_price": 0.95,
      "shares": 48543,
      "pl": -3883.44,
      "pl_pct": -7.77,
      "sell_reason": "月RSI4=50<77"
    },
    {
      "ticker": "044772",
      "buy_date": "2011-10-24",
      "buy_price": 3.45,
      "sell_date": "2011-10-25",
      "sell_price": 3.27,
      "shares": 14492,
      "pl": -2608.56,
      "pl_pct": -5.22,
      "sell_reason": "月RSI4=50<77"
    },
    {
      "ticker": "044510",
      "buy_date": "2011-10-25",
      "buy_price": 0.96,
      "sell_date": "2011-10-26",
      "sell_price": 0.91,
      "shares": 52083,
      "pl": -2604.15,
      "pl_pct": -5.21,
      "sell_reason": "月RSI4=50<77"
    },
    {
      "ticker": "044667",
      "buy_date": "2011-10-25",
      "buy_price": 2.18,
      "sell_date": "2011-10-26",
      "sell_price": 2.21,
      "shares": 22935,
      "pl": 688.05,
      "pl_pct": 1.38,
      "sell_reason": "月RSI4=50<77"
    },
    {
      "ticker": "044633",
      "buy_date": "2011-10-25",
      "buy_price": 0.42,
      "sell_date": "2011-10-26",
      "sell_price": 0.42,
      "shares": 119047,
      "pl": 0.0,
      "pl_pct": 0.0,
      "sell_reason": "月RSI4=50<77"
    },
    {
      "ticker": "044958",
      "buy_date": "2011-10-25",
      "buy_price": 2.83,
      "sell_date": "2011-10-26",
      "sell_price": 2.73,
      "shares": 17667,
      "pl": -1766.7,
      "pl_pct": -3.53,
      "sell_reason": "月RSI4=50<77"
    },
    {
      "ticker": "044393",
      "buy_date": "2011-10-25",
      "buy_price": 0.97,
      "sell_date": "2011-10-26",
      "sell_price": 0.95,
      "shares": 51546,
      "pl": -1030.92,
      "pl_pct": -2.06,
      "sell_reason": "月RSI4=50<77"
    },
    {
      "ticker": "044924",
      "buy_date": "2011-10-26",
      "buy_price": 0.49,
      "sell_date": "2011-10-27",
      "sell_price": 0.53,
      "shares": 102040,
      "pl": 4081.6,
      "pl_pct": 8.16,
      "sell_reason": "月RSI4=50<77"
    },
    {
      "ticker": "042699",
      "buy_date": "2011-10-26",
      "buy_price": 0.54,
      "sell_date": "2011-10-27",
      "sell_price": 0.5,
      "shares": 92592,
      "pl": -3703.68,
      "pl_pct": -7.41,
      "sell_reason": "月RSI4=50<77"
    },
    {
      "ticker": "043592",
      "buy_date": "2011-10-26",
      "buy_price": 0.51,
      "sell_date": "2011-10-27",
      "sell_price": 0.55,
      "shares": 98039,
      "pl": 3921.56,
      "pl_pct": 7.84,
      "sell_reason": "月RSI4=50<77"
    },
    {
      "ticker": "2302",
      "buy_date": "2011-10-26",
      "buy_price": 4.7,
      "sell_date": "2011-10-27",
      "sell_price": 4.79,
      "shares": 10638,
      "pl": 957.42,
      "pl_pct": 1.91,
      "sell_reason": "月RSI4=50<77"
    },
    {
      "ticker": "2606",
      "buy_date": "2011-10-26",
      "buy_price": 47.8,
      "sell_date": "2011-10-27",
      "sell_price": 48.15,
      "shares": 1046,
      "pl": 366.1,
      "pl_pct": 0.73,
      "sell_reason": "月RSI4=50<77"
    },
    {
      "ticker": "043239",
      "buy_date": "2011-10-27",
      "buy_price": 1.63,
      "sell_date": "2011-10-28",
      "sell_price": 1.7,
      "shares": 30674,
      "pl": 2147.18,
      "pl_pct": 4.29,
      "sell_reason": "月RSI4=50<77"
    },
    {
      "ticker": "042652",
      "buy_date": "2011-10-27",
      "buy_price": 0.37,
      "sell_date": "2011-10-28",
      "sell_price": 0.4,
      "shares": 135135,
      "pl": 4054.05,
      "pl_pct": 8.11,
      "sell_reason": "月RSI4=50<77"
    },
    {
      "ticker": "043392",
      "buy_date": "2011-10-27",
      "buy_price": 0.18,
      "sell_date": "2011-10-28",
      "sell_price": 0.14,
      "shares": 277777,
      "pl": -11111.08,
      "pl_pct": -22.22,
      "sell_reason": "止損-22.2%"
    },
    {
      "ticker": "044597",
      "buy_date": "2011-10-27",
      "buy_price": 1.26,
      "sell_date": "2011-10-28",
      "sell_price": 1.15,
      "shares": 39682,
      "pl": -4365.02,
      "pl_pct": -8.73,
      "sell_reason": "月RSI4=50<77"
    },
    {
      "ticker": "043328",
      "buy_date": "2011-10-27",
      "buy_price": 0.4,
      "sell_date": "2011-10-31",
      "sell_price": 0.39,
      "shares": 124999,
      "pl": -1249.99,
      "pl_pct": -2.5,
      "sell_reason": "月RSI4=50<77"
    },
    {
      "ticker": "1451",
      "buy_date": "2011-10-28",
      "buy_price": 21.5,
      "sell_date": "2011-10-31",
      "sell_price": 21.45,
      "shares": 2325,
      "pl": -116.25,
      "pl_pct": -0.23,
      "sell_reason": "月RSI4=50<77"
    },
    {
      "ticker": "045289",
      "buy_date": "2011-10-28",
      "buy_price": 0.84,
      "sell_date": "2011-10-31",
      "sell_price": 0.87,
      "shares": 59523,
      "pl": 1785.69,
      "pl_pct": 3.57,
      "sell_reason": "月RSI4=50<77"
    },
    {
      "ticker": "044909",
      "buy_date": "2011-10-28",
      "buy_price": 0.66,
      "sell_date": "2011-10-31",
      "sell_price": 0.68,
      "shares": 75757,
      "pl": 1515.14,
      "pl_pct": 3.03,
      "sell_reason": "月RSI4=50<77"
    },
    {
      "ticker": "041442",
      "buy_date": "2011-10-28",
      "buy_price": 0.7,
      "sell_date": "2011-10-31",
      "sell_price": 0.59,
      "shares": 71428,
      "pl": -7857.08,
      "pl_pct": -15.71,
      "sell_reason": "止損-15.7%"
    },
    {
      "ticker": "041090",
      "buy_date": "2011-10-28",
      "buy_price": 0.59,
      "sell_date": "2011-10-31",
      "sell_price": 0.52,
      "shares": 84745,
      "pl": -5932.15,
      "pl_pct": -11.86,
      "sell_reason": "止損-11.9%"
    },
    {
      "ticker": "1465",
      "buy_date": "2011-10-31",
      "buy_price": 14.2,
      "sell_date": "2011-11-01",
      "sell_price": 14.1,
      "shares": 3521,
      "pl": -352.1,
      "pl_pct": -0.7,
      "sell_reason": "月RSI4=50<77"
    },
    {
      "ticker": "041411",
      "buy_date": "2011-10-31",
      "buy_price": 0.33,
      "sell_date": "2011-11-01",
      "sell_price": 0.35,
      "shares": 151515,
      "pl": 3030.3,
      "pl_pct": 6.06,
      "sell_reason": "月RSI4=50<77"
    },
    {
      "ticker": "042763",
      "buy_date": "2011-10-31",
      "buy_price": 0.47,
      "sell_date": "2011-11-01",
      "sell_price": 0.45,
      "shares": 106382,
      "pl": -2127.64,
      "pl_pct": -4.26,
      "sell_reason": "月RSI4=50<77"
    },
    {
      "ticker": "041621",
      "buy_date": "2011-10-31",
      "buy_price": 0.27,
      "sell_date": "2011-11-01",
      "sell_price": 0.22,
      "shares": 185185,
      "pl": -9259.25,
      "pl_pct": -18.52,
      "sell_reason": "止損-18.5%"
    },
    {
      "ticker": "042199",
      "buy_date": "2011-10-31",
      "buy_price": 0.75,
      "sell_date": "2011-11-01",
      "sell_price": 0.79,
      "shares": 66666,
      "pl": 2666.64,
      "pl_pct": 5.33,
      "sell_reason": "月RSI4=50<77"
    },
    {
      "ticker": "044240",
      "buy_date": "2011-11-01",
      "buy_price": 1.25,
      "sell_date": "2011-11-02",
      "sell_price": 1.42,
      "shares": 40000,
      "pl": 6800.0,
      "pl_pct": 13.6,
      "sell_reason": "月RSI4=50<77"
    },
    {
      "ticker": "044204",
      "buy_date": "2011-11-01",
      "buy_price": 1.17,
      "sell_date": "2011-11-02",
      "sell_price": 1.13,
      "shares": 42735,
      "pl": -1709.4,
      "pl_pct": -3.42,
      "sell_reason": "月RSI4=50<77"
    },
    {
      "ticker": "044651",
      "buy_date": "2011-11-01",
      "buy_price": 1.97,
      "sell_date": "2011-11-02",
      "sell_price": 1.9,
      "shares": 25380,
      "pl": -1776.6,
      "pl_pct": -3.55,
      "sell_reason": "月RSI4=50<77"
    },
    {
      "ticker": "1909",
      "buy_date": "2011-11-01",
      "buy_price": 9.51,
      "sell_date": "2011-11-02",
      "sell_price": 9.52,
      "shares": 5257,
      "pl": 52.57,
      "pl_pct": 0.11,
      "sell_reason": "月RSI4=50<77"
    },
    {
      "ticker": "04636P",
      "buy_date": "2011-11-01",
      "buy_price": 2.8,
      "sell_date": "2011-11-02",
      "sell_price": 2.82,
      "shares": 17857,
      "pl": 357.14,
      "pl_pct": 0.71,
      "sell_reason": "月RSI4=50<77"
    },
    {
      "ticker": "044640",
      "buy_date": "2011-11-02",
      "buy_price": 1.22,
      "sell_date": "2011-11-03",
      "sell_price": 1.18,
      "shares": 40983,
      "pl": -1639.32,
      "pl_pct": -3.28,
      "sell_reason": "月RSI4=50<77"
    },
    {
      "ticker": "043364",
      "buy_date": "2011-11-02",
      "buy_price": 0.21,
      "sell_date": "2011-11-03",
      "sell_price": 0.18,
      "shares": 238095,
      "pl": -7142.85,
      "pl_pct": -14.29,
      "sell_reason": "止損-14.3%"
    },
    {
      "ticker": "043100",
      "buy_date": "2011-11-02",
      "buy_price": 0.19,
      "sell_date": "2011-11-03",
      "sell_price": 0.24,
      "shares": 263157,
      "pl": 13157.85,
      "pl_pct": 26.32,
      "sell_reason": "月RSI4=50<77"
    },
    {
      "ticker": "044353",
      "buy_date": "2011-11-02",
      "buy_price": 1.22,
      "sell_date": "2011-11-03",
      "sell_price": 1.08,
      "shares": 40983,
      "pl": -5737.62,
      "pl_pct": -11.48,
      "sell_reason": "止損-11.5%"
    },
    {
      "ticker": "9105",
      "buy_date": "2011-11-02",
      "buy_price": 3.02,
      "sell_date": "2011-11-03",
      "sell_price": 2.97,
      "shares": 16556,
      "pl": -827.8,
      "pl_pct": -1.66,
      "sell_reason": "月RSI4=50<77"
    },
    {
      "ticker": "043788",
      "buy_date": "2011-11-08",
      "buy_price": 1.03,
      "sell_date": "2011-11-09",
      "sell_price": 0.93,
      "shares": 48543,
      "pl": -4854.3,
      "pl_pct": -9.71,
      "sell_reason": "月RSI4=50<77"
    },
    {
      "ticker": "042596",
      "buy_date": "2011-11-08",
      "buy_price": 0.43,
      "sell_date": "2011-11-09",
      "sell_price": 0.32,
      "shares": 116279,
      "pl": -12790.69,
      "pl_pct": -25.58,
      "sell_reason": "止損-25.6%"
    },
    {
      "ticker": "045075",
      "buy_date": "2011-11-08",
      "buy_price": 1.01,
      "sell_date": "2011-11-09",
      "sell_price": 0.96,
      "shares": 49504,
      "pl": -2475.2,
      "pl_pct": -4.95,
      "sell_reason": "月RSI4=50<77"
    },
    {
      "ticker": "045038",
      "buy_date": "2011-11-08",
      "buy_price": 1.18,
      "sell_date": "2011-11-09",
      "sell_price": 1.25,
      "shares": 42372,
      "pl": 2966.04,
      "pl_pct": 5.93,
      "sell_reason": "月RSI4=50<77"
    },
    {
      "ticker": "042333",
      "buy_date": "2011-11-08",
      "buy_price": 0.17,
      "sell_date": "2011-11-10",
      "sell_price": 0.12,
      "shares": 294117,
      "pl": -14705.85,
      "pl_pct": -29.41,
      "sell_reason": "止損-29.4%"
    },
    {
      "ticker": "044037",
      "buy_date": "2011-11-09",
      "buy_price": 0.47,
      "sell_date": "2011-11-10",
      "sell_price": 0.4,
      "shares": 106382,
      "pl": -7446.74,
      "pl_pct": -14.89,
      "sell_reason": "止損-14.9%"
    },
    {
      "ticker": "045611",
      "buy_date": "2011-11-09",
      "buy_price": 0.81,
      "sell_date": "2011-11-10",
      "sell_price": 0.67,
      "shares": 61728,
      "pl": -8641.92,
      "pl_pct": -17.28,
      "sell_reason": "止損-17.3%"
    },
    {
      "ticker": "045590",
      "buy_date": "2011-11-09",
      "buy_price": 1.1,
      "sell_date": "2011-11-10",
      "sell_price": 0.95,
      "shares": 45454,
      "pl": -6818.1,
      "pl_pct": -13.64,
      "sell_reason": "止損-13.6%"
    },
    {
      "ticker": "044462",
      "buy_date": "2011-11-09",
      "buy_price": 0.47,
      "sell_date": "2011-11-10",
      "sell_price": 0.34,
      "shares": 106382,
      "pl": -13829.66,
      "pl_pct": -27.66,
      "sell_reason": "止損-27.7%"
    },
    {
      "ticker": "04972P",
      "buy_date": "2011-11-09",
      "buy_price": 1.67,
      "sell_date": "2011-11-10",
      "sell_price": 1.9,
      "shares": 29940,
      "pl": 6886.2,
      "pl_pct": 13.77,
      "sell_reason": "月RSI4=50<77"
    },
    {
      "ticker": "044401",
      "buy_date": "2011-12-26",
      "buy_price": 0.35,
      "sell_date": "2011-12-27",
      "sell_price": 0.36,
      "shares": 142857,
      "pl": 1428.57,
      "pl_pct": 2.86,
      "sell_reason": "月RSI4=50<77"
    },
    {
      "ticker": "044407",
      "buy_date": "2011-12-26",
      "buy_price": 0.26,
      "sell_date": "2011-12-27",
      "sell_price": 0.24,
      "shares": 192307,
      "pl": -3846.14,
      "pl_pct": -7.69,
      "sell_reason": "月RSI4=50<77"
    },
    {
      "ticker": "3025",
      "buy_date": "2011-12-26",
      "buy_price": 6.49,
      "sell_date": "2011-12-27",
      "sell_price": 6.44,
      "shares": 7704,
      "pl": -385.2,
      "pl_pct": -0.77,
      "sell_reason": "月RSI4=50<77"
    },
    {
      "ticker": "6197",
      "buy_date": "2011-12-26",
      "buy_price": 28.65,
      "sell_date": "2011-12-27",
      "sell_price": 28.45,
      "shares": 1745,
      "pl": -349.0,
      "pl_pct": -0.7,
      "sell_reason": "月RSI4=50<77"
    },
    {
      "ticker": "1215",
      "buy_date": "2011-12-26",
      "buy_price": 14.4,
      "sell_date": "2011-12-27",
      "sell_price": 14.25,
      "shares": 3472,
      "pl": -520.8,
      "pl_pct": -1.04,
      "sell_reason": "月RSI4=50<77"
    },
    {
      "ticker": "044401",
      "buy_date": "2011-12-27",
      "buy_price": 0.36,
      "sell_date": "2011-12-28",
      "sell_price": 0.39,
      "shares": 138888,
      "pl": 4166.64,
      "pl_pct": 8.33,
      "sell_reason": "月RSI4=50<77"
    },
    {
      "ticker": "045834",
      "buy_date": "2011-12-27",
      "buy_price": 1.21,
      "sell_date": "2011-12-28",
      "sell_price": 1.01,
      "shares": 41322,
      "pl": -8264.4,
      "pl_pct": -16.53,
      "sell_reason": "止損-16.5%"
    },
    {
      "ticker": "046999",
      "buy_date": "2011-12-27",
      "buy_price": 1.55,
      "sell_date": "2011-12-28",
      "sell_price": 1.48,
      "shares": 32258,
      "pl": -2258.06,
      "pl_pct": -4.52,
      "sell_reason": "月RSI4=50<77"
    },
    {
      "ticker": "045741",
      "buy_date": "2011-12-27",
      "buy_price": 0.63,
      "sell_date": "2011-12-28",
      "sell_price": 0.6,
      "shares": 79365,
      "pl": -2380.95,
      "pl_pct": -4.76,
      "sell_reason": "月RSI4=50<77"
    },
    {
      "ticker": "045568",
      "buy_date": "2011-12-27",
      "buy_price": 0.38,
      "sell_date": "2011-12-28",
      "sell_price": 0.29,
      "shares": 131578,
      "pl": -11842.02,
      "pl_pct": -23.68,
      "sell_reason": "止損-23.7%"
    },
    {
      "ticker": "2613",
      "buy_date": "2011-12-28",
      "buy_price": 14.0,
      "sell_date": "2011-12-29",
      "sell_price": 14.0,
      "shares": 3571,
      "pl": 0.0,
      "pl_pct": 0.0,
      "sell_reason": "月RSI4=50<77"
    },
    {
      "ticker": "044401",
      "buy_date": "2011-12-28",
      "buy_price": 0.39,
      "sell_date": "2011-12-29",
      "sell_price": 0.37,
      "shares": 128205,
      "pl": -2564.1,
      "pl_pct": -5.13,
      "sell_reason": "月RSI4=50<77"
    },
    {
      "ticker": "04943P",
      "buy_date": "2011-12-28",
      "buy_price": 0.59,
      "sell_date": "2011-12-29",
      "sell_price": 0.51,
      "shares": 84745,
      "pl": -6779.6,
      "pl_pct": -13.56,
      "sell_reason": "止損-13.6%"
    },
    {
      "ticker": "03030B",
      "buy_date": "2011-12-28",
      "buy_price": 5.9,
      "sell_date": "2011-12-29",
      "sell_price": 5.6,
      "shares": 8474,
      "pl": -2542.2,
      "pl_pct": -5.08,
      "sell_reason": "月RSI4=50<77"
    },
    {
      "ticker": "04901P",
      "buy_date": "2011-12-28",
      "buy_price": 1.49,
      "sell_date": "2011-12-29",
      "sell_price": 1.6,
      "shares": 33557,
      "pl": 3691.27,
      "pl_pct": 7.38,
      "sell_reason": "月RSI4=50<77"
    },
    {
      "ticker": "04901P",
      "buy_date": "2011-12-29",
      "buy_price": 1.6,
      "sell_date": "2011-12-30",
      "sell_price": 1.6,
      "shares": 31249,
      "pl": 0.0,
      "pl_pct": 0.0,
      "sell_reason": "月RSI4=50<77"
    },
    {
      "ticker": "913889",
      "buy_date": "2011-12-29",
      "buy_price": 6.42,
      "sell_date": "2011-12-30",
      "sell_price": 6.6,
      "shares": 7788,
      "pl": 1401.84,
      "pl_pct": 2.8,
      "sell_reason": "月RSI4=50<77"
    },
    {
      "ticker": "1325",
      "buy_date": "2011-12-29",
      "buy_price": 18.2,
      "sell_date": "2011-12-30",
      "sell_price": 18.5,
      "shares": 2747,
      "pl": 824.1,
      "pl_pct": 1.65,
      "sell_reason": "月RSI4=50<77"
    },
    {
      "ticker": "04713P",
      "buy_date": "2011-12-29",
      "buy_price": 3.4,
      "sell_date": "2011-12-30",
      "sell_price": 2.93,
      "shares": 14705,
      "pl": -6911.35,
      "pl_pct": -13.82,
      "sell_reason": "止損-13.8%"
    },
    {
      "ticker": "05388P",
      "buy_date": "2011-12-29",
      "buy_price": 0.79,
      "sell_date": "2011-12-30",
      "sell_price": 0.8,
      "shares": 63291,
      "pl": 632.91,
      "pl_pct": 1.27,
      "sell_reason": "月RSI4=50<77"
    },
    {
      "ticker": "034426",
      "buy_date": "2011-04-27",
      "buy_price": 2.75,
      "sell_date": "2011-12-30 (年終)",
      "sell_price": 2.75,
      "shares": 18181,
      "pl": 0.0,
      "pl_pct": 0.0,
      "sell_reason": "年終結算",
      "peak_price": 2.75
    },
    {
      "ticker": "913889",
      "buy_date": "2011-12-30",
      "buy_price": 6.6,
      "sell_date": "2011-12-30 (年終)",
      "sell_price": 6.6,
      "shares": 7575,
      "pl": 0.0,
      "pl_pct": 0.0,
      "sell_reason": "年終結算",
      "peak_price": 6.6
    },
    {
      "ticker": "044744",
      "buy_date": "2011-12-30",
      "buy_price": 0.49,
      "sell_date": "2011-12-30 (年終)",
      "sell_price": 0.49,
      "shares": 102040,
      "pl": 0.0,
      "pl_pct": 0.0,
      "sell_reason": "年終結算",
      "peak_price": 0.49
    },
    {
      "ticker": "046285",
      "buy_date": "2011-12-30",
      "buy_price": 0.55,
      "sell_date": "2011-12-30 (年終)",
      "sell_price": 0.55,
      "shares": 90909,
      "pl": 0.0,
      "pl_pct": 0.0,
      "sell_reason": "年終結算",
      "peak_price": 0.55
    },
    {
      "ticker": "1325",
      "buy_date": "2011-12-30",
      "buy_price": 18.5,
      "sell_date": "2011-12-30 (年終)",
      "sell_price": 18.5,
      "shares": 2702,
      "pl": 0.0,
      "pl_pct": 0.0,
      "sell_reason": "年終結算",
      "peak_price": 18.5
    },
    {
      "ticker": "03099C",
      "buy_date": "2011-12-30",
      "buy_price": 1.36,
      "sell_date": "2011-12-30 (年終)",
      "sell_price": 1.36,
      "shares": 36764,
      "pl": 0.0,
      "pl_pct": 0.0,
      "sell_reason": "年終結算",
      "peak_price": 1.36
    }
  ],
  "equity_curve": [
    {
      "date": "2011-01-03",
      "equity": 1000000.0,
      "type": "daily"
    },
    {
      "date": "2011-01-10",
      "equity": 1000000.0,
      "type": "daily"
    },
    {
      "date": "2011-01-17",
      "equity": 1000000.0,
      "type": "daily"
    },
    {
      "date": "2011-01-24",
      "equity": 1000000.0,
      "type": "daily"
    },
    {
      "date": "2011-02-08",
      "equity": 964350.98,
      "type": "daily"
    },
    {
      "date": "2011-02-15",
      "equity": 930519.3,
      "type": "daily"
    },
    {
      "date": "2011-02-22",
      "equity": 930519.3,
      "type": "daily"
    },
    {
      "date": "2011-03-02",
      "equity": 930519.3,
      "type": "daily"
    },
    {
      "date": "2011-03-09",
      "equity": 930519.3,
      "type": "daily"
    },
    {
      "date": "2011-03-16",
      "equity": 930519.3,
      "type": "daily"
    },
    {
      "date": "2011-03-23",
      "equity": 930519.3,
      "type": "daily"
    },
    {
      "date": "2011-03-30",
      "equity": 930519.3,
      "type": "daily"
    },
    {
      "date": "2011-04-08",
      "equity": 1006088.32,
      "type": "daily"
    },
    {
      "date": "2011-04-15",
      "equity": 986652.58,
      "type": "daily"
    },
    {
      "date": "2011-04-22",
      "equity": 1029140.24,
      "type": "daily"
    },
    {
      "date": "2011-04-29",
      "equity": 993521.9,
      "type": "daily"
    },
    {
      "date": "2011-05-09",
      "equity": 1073783.33,
      "type": "daily"
    },
    {
      "date": "2011-05-16",
      "equity": 1036435.15,
      "type": "daily"
    },
    {
      "date": "2011-05-23",
      "equity": 1036435.15,
      "type": "daily"
    },
    {
      "date": "2011-05-30",
      "equity": 1036435.15,
      "type": "daily"
    },
    {
      "date": "2011-06-07",
      "equity": 1021647.5,
      "type": "daily"
    },
    {
      "date": "2011-06-14",
      "equity": 971283.11,
      "type": "daily"
    },
    {
      "date": "2011-06-21",
      "equity": 971283.11,
      "type": "daily"
    },
    {
      "date": "2011-06-28",
      "equity": 956445.35,
      "type": "daily"
    },
    {
      "date": "2011-07-05",
      "equity": 956445.35,
      "type": "daily"
    },
    {
      "date": "2011-07-12",
      "equity": 956445.35,
      "type": "daily"
    },
    {
      "date": "2011-07-19",
      "equity": 956445.35,
      "type": "daily"
    },
    {
      "date": "2011-07-26",
      "equity": 942764.07,
      "type": "daily"
    },
    {
      "date": "2011-08-02",
      "equity": 972997.78,
      "type": "daily"
    },
    {
      "date": "2011-08-09",
      "equity": 972997.78,
      "type": "daily"
    },
    {
      "date": "2011-08-16",
      "equity": 972997.78,
      "type": "daily"
    },
    {
      "date": "2011-08-23",
      "equity": 972997.78,
      "type": "daily"
    },
    {
      "date": "2011-08-30",
      "equity": 972997.78,
      "type": "daily"
    },
    {
      "date": "2011-09-06",
      "equity": 972997.78,
      "type": "daily"
    },
    {
      "date": "2011-09-14",
      "equity": 972997.78,
      "type": "daily"
    },
    {
      "date": "2011-09-21",
      "equity": 978660.38,
      "type": "daily"
    },
    {
      "date": "2011-09-28",
      "equity": 994951.96,
      "type": "daily"
    },
    {
      "date": "2011-10-05",
      "equity": 994951.96,
      "type": "daily"
    },
    {
      "date": "2011-10-13",
      "equity": 1002193.68,
      "type": "daily"
    },
    {
      "date": "2011-10-20",
      "equity": 933139.54,
      "type": "daily"
    },
    {
      "date": "2011-10-27",
      "equity": 926865.62,
      "type": "daily"
    },
    {
      "date": "2011-11-03",
      "equity": 901228.03,
      "type": "daily"
    },
    {
      "date": "2011-11-10",
      "equity": 839517.81,
      "type": "daily"
    },
    {
      "date": "2011-11-17",
      "equity": 839517.81,
      "type": "daily"
    },
    {
      "date": "2011-11-24",
      "equity": 839517.81,
      "type": "daily"
    },
    {
      "date": "2011-12-01",
      "equity": 839517.81,
      "type": "daily"
    },
    {
      "date": "2011-12-08",
      "equity": 839517.81,
      "type": "daily"
    },
    {
      "date": "2011-12-15",
      "equity": 839517.81,
      "type": "daily"
    },
    {
      "date": "2011-12-22",
      "equity": 839517.81,
      "type": "daily"
    },
    {
      "date": "2011-12-29",
      "equity": 807071.83,
      "type": "daily"
    },
    {
      "date": "2011-12-31",
      "equity": 803019.33,
      "type": "final"
    }
  ],
  "missed_trades": []
}