{
  "trades": [
    {
      "ticker": "045834",
      "buy_date": "2012-02-22",
      "buy_price": 2.23,
      "sell_date": "2012-02-23",
      "sell_price": 1.95,
      "shares": 22421,
      "pl": -6277.88,
      "pl_pct": -12.56,
      "sell_reason": "止損-12.6%"
    },
    {
      "ticker": "3519",
      "buy_date": "2012-02-22",
      "buy_price": 44.58,
      "sell_date": "2012-02-23",
      "sell_price": 42.4,
      "shares": 1121,
      "pl": -2443.43,
      "pl_pct": -4.89,
      "sell_reason": "月RSI4=50<77"
    },
    {
      "ticker": "047158",
      "buy_date": "2012-02-22",
      "buy_price": 0.7,
      "sell_date": "2012-02-23",
      "sell_price": 0.98,
      "shares": 71428,
      "pl": 19999.84,
      "pl_pct": 40.0,
      "sell_reason": "月RSI4=50<77"
    },
    {
      "ticker": "6271",
      "buy_date": "2012-02-22",
      "buy_price": 100.44,
      "sell_date": "2012-02-23",
      "sell_price": 98.04,
      "shares": 497,
      "pl": -1194.28,
      "pl_pct": -2.39,
      "sell_reason": "月RSI4=50<77"
    },
    {
      "ticker": "8210",
      "buy_date": "2012-02-22",
      "buy_price": 33.28,
      "sell_date": "2012-02-23",
      "sell_price": 33.23,
      "shares": 1502,
      "pl": -67.46,
      "pl_pct": -0.13,
      "sell_reason": "月RSI4=50<77"
    },
    {
      "ticker": "045813",
      "buy_date": "2012-02-23",
      "buy_price": 1.14,
      "sell_date": "2012-02-24",
      "sell_price": 0.99,
      "shares": 43859,
      "pl": -6578.85,
      "pl_pct": -13.16,
      "sell_reason": "止損-13.2%"
    },
    {
      "ticker": "046079",
      "buy_date": "2012-02-23",
      "buy_price": 0.87,
      "sell_date": "2012-02-24",
      "sell_price": 0.76,
      "shares": 57471,
      "pl": -6321.81,
      "pl_pct": -12.64,
      "sell_reason": "止損-12.6%"
    },
    {
      "ticker": "046038",
      "buy_date": "2012-02-23",
      "buy_price": 1.72,
      "sell_date": "2012-02-24",
      "sell_price": 1.57,
      "shares": 29069,
      "pl": -4360.35,
      "pl_pct": -8.72,
      "sell_reason": "月RSI4=50<77"
    },
    {
      "ticker": "5706",
      "buy_date": "2012-02-23",
      "buy_price": 73.0,
      "sell_date": "2012-02-24",
      "sell_price": 71.8,
      "shares": 684,
      "pl": -820.8,
      "pl_pct": -1.64,
      "sell_reason": "月RSI4=50<77"
    },
    {
      "ticker": "045378",
      "buy_date": "2012-02-23",
      "buy_price": 1.47,
      "sell_date": "2012-02-29",
      "sell_price": 1.18,
      "shares": 34013,
      "pl": -9863.77,
      "pl_pct": -19.73,
      "sell_reason": "止損-19.7%"
    },
    {
      "ticker": "1316",
      "buy_date": "2012-02-24",
      "buy_price": 23.3,
      "sell_date": "2012-02-29",
      "sell_price": 24.9,
      "shares": 2145,
      "pl": 3432.0,
      "pl_pct": 6.87,
      "sell_reason": "月RSI4=50<77"
    },
    {
      "ticker": "047906",
      "buy_date": "2012-02-24",
      "buy_price": 3.73,
      "sell_date": "2012-02-29",
      "sell_price": 3.85,
      "shares": 13404,
      "pl": 1608.48,
      "pl_pct": 3.22,
      "sell_reason": "月RSI4=50<77"
    },
    {
      "ticker": "1531",
      "buy_date": "2012-02-24",
      "buy_price": 24.1,
      "sell_date": "2012-02-29",
      "sell_price": 23.95,
      "shares": 2074,
      "pl": -311.1,
      "pl_pct": -0.62,
      "sell_reason": "月RSI4=50<77"
    },
    {
      "ticker": "3312",
      "buy_date": "2012-02-24",
      "buy_price": 12.45,
      "sell_date": "2012-02-29",
      "sell_price": 12.3,
      "shares": 4016,
      "pl": -602.4,
      "pl_pct": -1.2,
      "sell_reason": "月RSI4=50<77"
    },
    {
      "ticker": "047961",
      "buy_date": "2012-02-24",
      "buy_price": 4.6,
      "sell_date": "2012-02-29",
      "sell_price": 5.35,
      "shares": 10869,
      "pl": 8151.75,
      "pl_pct": 16.3,
      "sell_reason": "月RSI4=50<77"
    },
    {
      "ticker": "045683",
      "buy_date": "2012-02-29",
      "buy_price": 0.8,
      "sell_date": "2012-03-01",
      "sell_price": 0.73,
      "shares": 62499,
      "pl": -4374.93,
      "pl_pct": -8.75,
      "sell_reason": "月RSI4=50<77"
    },
    {
      "ticker": "048043",
      "buy_date": "2012-02-29",
      "buy_price": 1.45,
      "sell_date": "2012-03-01",
      "sell_price": 1.37,
      "shares": 34482,
      "pl": -2758.56,
      "pl_pct": -5.52,
      "sell_reason": "月RSI4=50<77"
    },
    {
      "ticker": "046031",
      "buy_date": "2012-02-29",
      "buy_price": 0.87,
      "sell_date": "2012-03-01",
      "sell_price": 0.94,
      "shares": 57471,
      "pl": 4022.97,
      "pl_pct": 8.05,
      "sell_reason": "月RSI4=50<77"
    },
    {
      "ticker": "046062",
      "buy_date": "2012-02-29",
      "buy_price": 0.69,
      "sell_date": "2012-03-01",
      "sell_price": 0.71,
      "shares": 72463,
      "pl": 1449.26,
      "pl_pct": 2.9,
      "sell_reason": "月RSI4=50<77"
    },
    {
      "ticker": "048113",
      "buy_date": "2012-02-29",
      "buy_price": 1.0,
      "sell_date": "2012-03-01",
      "sell_price": 1.0,
      "shares": 50000,
      "pl": 0.0,
      "pl_pct": 0.0,
      "sell_reason": "月RSI4=50<77"
    },
    {
      "ticker": "044813",
      "buy_date": "2012-03-01",
      "buy_price": 1.56,
      "sell_date": "2012-03-02",
      "sell_price": 1.27,
      "shares": 32051,
      "pl": -9294.79,
      "pl_pct": -18.59,
      "sell_reason": "止損-18.6%"
    },
    {
      "ticker": "046232",
      "buy_date": "2012-03-01",
      "buy_price": 2.22,
      "sell_date": "2012-03-02",
      "sell_price": 2.13,
      "shares": 22522,
      "pl": -2026.98,
      "pl_pct": -4.05,
      "sell_reason": "月RSI4=50<77"
    },
    {
      "ticker": "045076",
      "buy_date": "2012-03-01",
      "buy_price": 0.74,
      "sell_date": "2012-03-02",
      "sell_price": 0.59,
      "shares": 67567,
      "pl": -10135.05,
      "pl_pct": -20.27,
      "sell_reason": "止損-20.3%"
    },
    {
      "ticker": "046225",
      "buy_date": "2012-03-01",
      "buy_price": 0.75,
      "sell_date": "2012-03-02",
      "sell_price": 0.63,
      "shares": 66666,
      "pl": -7999.92,
      "pl_pct": -16.0,
      "sell_reason": "止損-16.0%"
    },
    {
      "ticker": "046442",
      "buy_date": "2012-03-01",
      "buy_price": 1.01,
      "sell_date": "2012-03-02",
      "sell_price": 0.91,
      "shares": 49504,
      "pl": -4950.4,
      "pl_pct": -9.9,
      "sell_reason": "月RSI4=50<77"
    },
    {
      "ticker": "041932",
      "buy_date": "2012-03-02",
      "buy_price": 0.63,
      "sell_date": "2012-03-05",
      "sell_price": 1.08,
      "shares": 79365,
      "pl": 35714.25,
      "pl_pct": 71.43,
      "sell_reason": "月RSI4=50<77"
    },
    {
      "ticker": "045845",
      "buy_date": "2012-03-02",
      "buy_price": 0.92,
      "sell_date": "2012-03-05",
      "sell_price": 0.63,
      "shares": 54347,
      "pl": -15760.63,
      "pl_pct": -31.52,
      "sell_reason": "止損-31.5%"
    },
    {
      "ticker": "047725",
      "buy_date": "2012-03-02",
      "buy_price": 2.81,
      "sell_date": "2012-03-05",
      "sell_price": 2.8,
      "shares": 17793,
      "pl": -177.93,
      "pl_pct": -0.36,
      "sell_reason": "月RSI4=50<77"
    },
    {
      "ticker": "048158",
      "buy_date": "2012-03-02",
      "buy_price": 2.61,
      "sell_date": "2012-03-05",
      "sell_price": 2.64,
      "shares": 19157,
      "pl": 574.71,
      "pl_pct": 1.15,
      "sell_reason": "月RSI4=50<77"
    },
    {
      "ticker": "046713",
      "buy_date": "2012-03-05",
      "buy_price": 1.07,
      "sell_date": "2012-03-06",
      "sell_price": 1.09,
      "shares": 46728,
      "pl": 934.56,
      "pl_pct": 1.87,
      "sell_reason": "月RSI4=50<77"
    },
    {
      "ticker": "047798",
      "buy_date": "2012-03-05",
      "buy_price": 1.7,
      "sell_date": "2012-03-06",
      "sell_price": 1.52,
      "shares": 29411,
      "pl": -5293.98,
      "pl_pct": -10.59,
      "sell_reason": "止損-10.6%"
    },
    {
      "ticker": "1203",
      "buy_date": "2012-03-05",
      "buy_price": 22.35,
      "sell_date": "2012-03-06",
      "sell_price": 22.0,
      "shares": 2237,
      "pl": -782.95,
      "pl_pct": -1.57,
      "sell_reason": "月RSI4=50<77"
    },
    {
      "ticker": "1104",
      "buy_date": "2012-03-05",
      "buy_price": 15.02,
      "sell_date": "2012-03-06",
      "sell_price": 14.68,
      "shares": 3329,
      "pl": -1125.13,
      "pl_pct": -2.25,
      "sell_reason": "月RSI4=50<77"
    },
    {
      "ticker": "6116",
      "buy_date": "2012-03-05",
      "buy_price": 3.53,
      "sell_date": "2012-03-06",
      "sell_price": 3.61,
      "shares": 14164,
      "pl": 1133.12,
      "pl_pct": 2.27,
      "sell_reason": "月RSI4=50<77"
    },
    {
      "ticker": "045361",
      "buy_date": "2012-03-02",
      "buy_price": 1.81,
      "sell_date": "2012-03-07",
      "sell_price": 1.53,
      "shares": 27624,
      "pl": -7734.72,
      "pl_pct": -15.47,
      "sell_reason": "止損-15.5%"
    },
    {
      "ticker": "046735",
      "buy_date": "2012-03-09",
      "buy_price": 2.27,
      "sell_date": "2012-03-12",
      "sell_price": 2.29,
      "shares": 22026,
      "pl": 440.52,
      "pl_pct": 0.88,
      "sell_reason": "月RSI4=50<77"
    },
    {
      "ticker": "05546P",
      "buy_date": "2012-03-09",
      "buy_price": 1.07,
      "sell_date": "2012-03-12",
      "sell_price": 1.08,
      "shares": 46728,
      "pl": 467.28,
      "pl_pct": 0.93,
      "sell_reason": "月RSI4=50<77"
    },
    {
      "ticker": "05352P",
      "buy_date": "2012-03-09",
      "buy_price": 1.13,
      "sell_date": "2012-03-12",
      "sell_price": 1.11,
      "shares": 44247,
      "pl": -884.94,
      "pl_pct": -1.77,
      "sell_reason": "月RSI4=50<77"
    },
    {
      "ticker": "1423",
      "buy_date": "2012-03-09",
      "buy_price": 8.23,
      "sell_date": "2012-03-12",
      "sell_price": 8.18,
      "shares": 6075,
      "pl": -303.75,
      "pl_pct": -0.61,
      "sell_reason": "月RSI4=50<77"
    },
    {
      "ticker": "9917",
      "buy_date": "2012-03-09",
      "buy_price": 59.8,
      "sell_date": "2012-03-12",
      "sell_price": 59.8,
      "shares": 836,
      "pl": 0.0,
      "pl_pct": 0.0,
      "sell_reason": "月RSI4=50<77"
    },
    {
      "ticker": "047628",
      "buy_date": "2012-03-13",
      "buy_price": 1.93,
      "sell_date": "2012-03-14",
      "sell_price": 2.06,
      "shares": 25906,
      "pl": 3367.78,
      "pl_pct": 6.74,
      "sell_reason": "月RSI4=50<77"
    },
    {
      "ticker": "6184",
      "buy_date": "2012-03-13",
      "buy_price": 50.69,
      "sell_date": "2012-03-14",
      "sell_price": 50.87,
      "shares": 986,
      "pl": 175.99,
      "pl_pct": 0.35,
      "sell_reason": "月RSI4=50<77"
    },
    {
      "ticker": "05352P",
      "buy_date": "2012-03-13",
      "buy_price": 1.16,
      "sell_date": "2012-03-14",
      "sell_price": 1.06,
      "shares": 43103,
      "pl": -4310.3,
      "pl_pct": -8.62,
      "sell_reason": "月RSI4=50<77"
    },
    {
      "ticker": "046710",
      "buy_date": "2012-03-13",
      "buy_price": 1.3,
      "sell_date": "2012-03-14",
      "sell_price": 1.31,
      "shares": 38461,
      "pl": 384.61,
      "pl_pct": 0.77,
      "sell_reason": "月RSI4=50<77"
    },
    {
      "ticker": "2369",
      "buy_date": "2012-03-13",
      "buy_price": 19.97,
      "sell_date": "2012-03-14",
      "sell_price": 19.53,
      "shares": 2503,
      "pl": -1102.53,
      "pl_pct": -2.21,
      "sell_reason": "月RSI4=50<77"
    },
    {
      "ticker": "048013",
      "buy_date": "2012-03-14",
      "buy_price": 1.44,
      "sell_date": "2012-03-15",
      "sell_price": 1.35,
      "shares": 34722,
      "pl": -3124.98,
      "pl_pct": -6.25,
      "sell_reason": "月RSI4=50<77"
    },
    {
      "ticker": "046572",
      "buy_date": "2012-03-14",
      "buy_price": 1.29,
      "sell_date": "2012-03-15",
      "sell_price": 1.25,
      "shares": 38759,
      "pl": -1550.36,
      "pl_pct": -3.1,
      "sell_reason": "月RSI4=50<77"
    },
    {
      "ticker": "047244",
      "buy_date": "2012-03-14",
      "buy_price": 3.16,
      "sell_date": "2012-03-15",
      "sell_price": 2.89,
      "shares": 15822,
      "pl": -4271.94,
      "pl_pct": -8.54,
      "sell_reason": "月RSI4=50<77"
    },
    {
      "ticker": "048436",
      "buy_date": "2012-03-14",
      "buy_price": 1.66,
      "sell_date": "2012-03-15",
      "sell_price": 1.57,
      "shares": 30120,
      "pl": -2710.8,
      "pl_pct": -5.42,
      "sell_reason": "月RSI4=50<77"
    },
    {
      "ticker": "048464",
      "buy_date": "2012-03-15",
      "buy_price": 1.27,
      "sell_date": "2012-03-16",
      "sell_price": 1.21,
      "shares": 39370,
      "pl": -2362.2,
      "pl_pct": -4.72,
      "sell_reason": "月RSI4=50<77"
    },
    {
      "ticker": "5471",
      "buy_date": "2012-03-15",
      "buy_price": 46.79,
      "sell_date": "2012-03-16",
      "sell_price": 46.41,
      "shares": 1068,
      "pl": -399.75,
      "pl_pct": -0.8,
      "sell_reason": "月RSI4=50<77"
    },
    {
      "ticker": "045760",
      "buy_date": "2012-03-15",
      "buy_price": 1.18,
      "sell_date": "2012-03-16",
      "sell_price": 1.12,
      "shares": 42372,
      "pl": -2542.32,
      "pl_pct": -5.08,
      "sell_reason": "月RSI4=50<77"
    },
    {
      "ticker": "3443",
      "buy_date": "2012-03-15",
      "buy_price": 122.5,
      "sell_date": "2012-03-16",
      "sell_price": 119.5,
      "shares": 408,
      "pl": -1224.0,
      "pl_pct": -2.45,
      "sell_reason": "月RSI4=50<77"
    },
    {
      "ticker": "046103",
      "buy_date": "2012-03-15",
      "buy_price": 4.96,
      "sell_date": "2012-03-16",
      "sell_price": 4.87,
      "shares": 10080,
      "pl": -907.2,
      "pl_pct": -1.81,
      "sell_reason": "月RSI4=50<77"
    },
    {
      "ticker": "047917",
      "buy_date": "2012-03-16",
      "buy_price": 1.56,
      "sell_date": "2012-03-19",
      "sell_price": 1.34,
      "shares": 32051,
      "pl": -7051.22,
      "pl_pct": -14.1,
      "sell_reason": "止損-14.1%"
    },
    {
      "ticker": "3257",
      "buy_date": "2012-03-16",
      "buy_price": 31.95,
      "sell_date": "2012-03-19",
      "sell_price": 31.3,
      "shares": 1564,
      "pl": -1016.6,
      "pl_pct": -2.03,
      "sell_reason": "月RSI4=50<77"
    },
    {
      "ticker": "048521",
      "buy_date": "2012-03-16",
      "buy_price": 2.95,
      "sell_date": "2012-03-19",
      "sell_price": 2.47,
      "shares": 16949,
      "pl": -8135.52,
      "pl_pct": -16.27,
      "sell_reason": "止損-16.3%"
    },
    {
      "ticker": "047804",
      "buy_date": "2012-03-16",
      "buy_price": 1.32,
      "sell_date": "2012-03-19",
      "sell_price": 1.32,
      "shares": 37878,
      "pl": 0.0,
      "pl_pct": 0.0,
      "sell_reason": "月RSI4=50<77"
    },
    {
      "ticker": "2328",
      "buy_date": "2012-03-16",
      "buy_price": 31.0,
      "sell_date": "2012-03-19",
      "sell_price": 29.9,
      "shares": 1612,
      "pl": -1773.2,
      "pl_pct": -3.55,
      "sell_reason": "月RSI4=50<77"
    },
    {
      "ticker": "047797",
      "buy_date": "2012-03-14",
      "buy_price": 1.17,
      "sell_date": "2012-03-21",
      "sell_price": 0.95,
      "shares": 42735,
      "pl": -9401.7,
      "pl_pct": -18.8,
      "sell_reason": "止損-18.8%"
    },
    {
      "ticker": "1419",
      "buy_date": "2012-03-22",
      "buy_price": 44.75,
      "sell_date": "2012-03-23",
      "sell_price": 44.75,
      "shares": 1117,
      "pl": 0.0,
      "pl_pct": 0.0,
      "sell_reason": "月RSI4=50<77"
    },
    {
      "ticker": "1806",
      "buy_date": "2012-03-22",
      "buy_price": 16.05,
      "sell_date": "2012-03-23",
      "sell_price": 16.2,
      "shares": 3115,
      "pl": 458.68,
      "pl_pct": 0.92,
      "sell_reason": "月RSI4=50<77"
    },
    {
      "ticker": "6230",
      "buy_date": "2012-03-22",
      "buy_price": 34.7,
      "sell_date": "2012-03-23",
      "sell_price": 33.87,
      "shares": 1440,
      "pl": -1201.52,
      "pl_pct": -2.4,
      "sell_reason": "月RSI4=50<77"
    },
    {
      "ticker": "2723",
      "buy_date": "2012-03-22",
      "buy_price": 230.22,
      "sell_date": "2012-03-23",
      "sell_price": 228.38,
      "shares": 217,
      "pl": -400.46,
      "pl_pct": -0.8,
      "sell_reason": "月RSI4=50<77"
    },
    {
      "ticker": "8016",
      "buy_date": "2012-03-22",
      "buy_price": 44.55,
      "sell_date": "2012-03-23",
      "sell_price": 45.4,
      "shares": 1122,
      "pl": 953.7,
      "pl_pct": 1.91,
      "sell_reason": "月RSI4=50<77"
    }
  ],
  "equity_curve": [
    {
      "date": "2012-01-02",
      "equity": 1000000.0,
      "type": "daily"
    },
    {
      "date": "2012-01-09",
      "equity": 1000000.0,
      "type": "daily"
    },
    {
      "date": "2012-01-16",
      "equity": 1000000.0,
      "type": "daily"
    },
    {
      "date": "2012-02-01",
      "equity": 1000000.0,
      "type": "daily"
    },
    {
      "date": "2012-02-08",
      "equity": 1000000.0,
      "type": "daily"
    },
    {
      "date": "2012-02-15",
      "equity": 1000000.0,
      "type": "daily"
    },
    {
      "date": "2012-02-22",
      "equity": 1000000.0,
      "type": "daily"
    },
    {
      "date": "2012-03-02",
      "equity": 958281.56,
      "type": "daily"
    },
    {
      "date": "2012-03-09",
      "equity": 965762.86,
      "type": "daily"
    },
    {
      "date": "2012-03-16",
      "equity": 944903.98,
      "type": "daily"
    },
    {
      "date": "2012-03-23",
      "equity": 917336.14,
      "type": "daily"
    },
    {
      "date": "2012-03-30",
      "equity": 917336.14,
      "type": "daily"
    },
    {
      "date": "2012-04-09",
      "equity": 917336.14,
      "type": "daily"
    },
    {
      "date": "2012-04-16",
      "equity": 917336.14,
      "type": "daily"
    },
    {
      "date": "2012-04-23",
      "equity": 917336.14,
      "type": "daily"
    },
    {
      "date": "2012-04-30",
      "equity": 917336.14,
      "type": "daily"
    },
    {
      "date": "2012-05-08",
      "equity": 917336.14,
      "type": "daily"
    },
    {
      "date": "2012-05-15",
      "equity": 917336.14,
      "type": "daily"
    },
    {
      "date": "2012-05-22",
      "equity": 917336.14,
      "type": "daily"
    },
    {
      "date": "2012-05-29",
      "equity": 917336.14,
      "type": "daily"
    },
    {
      "date": "2012-06-05",
      "equity": 917336.14,
      "type": "daily"
    },
    {
      "date": "2012-06-12",
      "equity": 917336.14,
      "type": "daily"
    },
    {
      "date": "2012-06-19",
      "equity": 917336.14,
      "type": "daily"
    },
    {
      "date": "2012-06-26",
      "equity": 917336.14,
      "type": "daily"
    },
    {
      "date": "2012-07-03",
      "equity": 917336.14,
      "type": "daily"
    },
    {
      "date": "2012-07-10",
      "equity": 917336.14,
      "type": "daily"
    },
    {
      "date": "2012-07-17",
      "equity": 917336.14,
      "type": "daily"
    },
    {
      "date": "2012-07-24",
      "equity": 917336.14,
      "type": "daily"
    },
    {
      "date": "2012-07-31",
      "equity": 917336.14,
      "type": "daily"
    },
    {
      "date": "2012-08-08",
      "equity": 917336.14,
      "type": "daily"
    },
    {
      "date": "2012-08-15",
      "equity": 917336.14,
      "type": "daily"
    },
    {
      "date": "2012-08-22",
      "equity": 917336.14,
      "type": "daily"
    },
    {
      "date": "2012-08-29",
      "equity": 917336.14,
      "type": "daily"
    },
    {
      "date": "2012-09-05",
      "equity": 917336.14,
      "type": "daily"
    },
    {
      "date": "2012-09-12",
      "equity": 917336.14,
      "type": "daily"
    },
    {
      "date": "2012-09-19",
      "equity": 917336.14,
      "type": "daily"
    },
    {
      "date": "2012-09-26",
      "equity": 917336.14,
      "type": "daily"
    },
    {
      "date": "2012-10-03",
      "equity": 917336.14,
      "type": "daily"
    },
    {
      "date": "2012-10-11",
      "equity": 917336.14,
      "type": "daily"
    },
    {
      "date": "2012-10-18",
      "equity": 917336.14,
      "type": "daily"
    },
    {
      "date": "2012-10-25",
      "equity": 917336.14,
      "type": "daily"
    },
    {
      "date": "2012-11-01",
      "equity": 917336.14,
      "type": "daily"
    },
    {
      "date": "2012-11-08",
      "equity": 917336.14,
      "type": "daily"
    },
    {
      "date": "2012-11-15",
      "equity": 917336.14,
      "type": "daily"
    },
    {
      "date": "2012-11-22",
      "equity": 917336.14,
      "type": "daily"
    },
    {
      "date": "2012-11-29",
      "equity": 917336.14,
      "type": "daily"
    },
    {
      "date": "2012-12-06",
      "equity": 917336.14,
      "type": "daily"
    },
    {
      "date": "2012-12-13",
      "equity": 917336.14,
      "type": "daily"
    },
    {
      "date": "2012-12-20",
      "equity": 917336.14,
      "type": "daily"
    },
    {
      "date": "2012-12-27",
      "equity": 917336.14,
      "type": "daily"
    },
    {
      "date": "2012-12-31",
      "equity": 917336.14,
      "type": "final"
    }
  ],
  "missed_trades": []
}